{
  "schemaVersion": 1,
  "snapshotDate": "2026-07-22",
  "collectedAt": "2026-07-22T04:20:12.070Z",
  "sourceUpdatedAt": "2026-07-21T21:20:11-07:00",
  "source": "Apple iTunes RSS",
  "sourceUrl": "https://itunes.apple.com/jp/rss/toppaidapplications/limit=100/genre=6023/json",
  "chartType": "paid",
  "market": {
    "code": "jp",
    "name": "日本",
    "group": "核心市场"
  },
  "category": {
    "key": "food-drink",
    "id": 6023,
    "name": "美食佳饮"
  },
  "requestedLimit": 100,
  "expectedCount": 99,
  "actualCount": 99,
  "status": "complete",
  "issues": [],
  "previousSnapshotDate": "2026-07-21",
  "apps": [
    {
      "rank": 1,
      "previousRank": 1,
      "rankChange": 0,
      "isNew": false,
      "appleId": "1303222868",
      "name": "Paprika レシピ・マネージャー３",
      "developer": "Hindsight Labs LLC",
      "developerUrl": "https://apps.apple.com/jp/developer/hindsight-labs-llc/id392408031?uo=2",
      "iconUrl": "https://is1-ssl.mzstatic.com/image/thumb/Purple221/v4/aa/d6/97/aad69734-b8e6-9cbe-77bd-98ce50bf5841/AppIcon-0-0-1x_U007emarketing-0-8-0-0-85-220.png/100x100bb.png",
      "storeUrl": "https://apps.apple.com/jp/app/paprika-%E3%83%AC%E3%82%B7%E3%83%94-%E3%83%9E%E3%83%8D%E3%83%BC%E3%82%B8%E3%83%A3%E3%83%BC%EF%BC%93/id1303222868?uo=2",
      "price": {
        "amount": 800,
        "currency": "JPY",
        "formatted": "¥800"
      },
      "primaryCategory": {
        "id": "6023",
        "name": "フード／ドリンク"
      },
      "releaseDate": "2017年11月15日"
    },
    {
      "rank": 2,
      "previousRank": 2,
      "rankChange": 0,
      "isNew": false,
      "appleId": "6786651700",
      "name": "プリフロ道場 - ポーカーGTOドリル",
      "developer": "Masahiro Akebi",
      "developerUrl": "https://apps.apple.com/jp/developer/masahiro-akebi/id1884865177?uo=2",
      "iconUrl": "https://is1-ssl.mzstatic.com/image/thumb/Purple221/v4/10/3d/68/103d68fd-218d-ff9c-bb10-ecbb84836d00/AppIcon-0-0-1x_U007emarketing-0-8-0-85-220.png/100x100bb.png",
      "storeUrl": "https://apps.apple.com/jp/app/%E3%83%97%E3%83%AA%E3%83%95%E3%83%AD%E9%81%93%E5%A0%B4-%E3%83%9D%E3%83%BC%E3%82%AB%E3%83%BCgto%E3%83%89%E3%83%AA%E3%83%AB/id6786651700?uo=2",
      "price": {
        "amount": 800,
        "currency": "JPY",
        "formatted": "¥800"
      },
      "primaryCategory": {
        "id": "6023",
        "name": "フード／ドリンク"
      },
      "releaseDate": "2026年7月7日"
    },
    {
      "rank": 3,
      "previousRank": 3,
      "rankChange": 0,
      "isNew": false,
      "appleId": "640670118",
      "name": "BeerSmith Mobile Home Brewing",
      "developer": "BeerSmith LLC",
      "developerUrl": "https://apps.apple.com/jp/developer/beersmith-llc/id566379732?uo=2",
      "iconUrl": "https://is1-ssl.mzstatic.com/image/thumb/Purple124/v4/f6/1e/f3/f61ef3a4-3c2f-37fd-c268-6120108a57ba/AppIcon-0-0-1x_U007emarketing-0-0-0-10-0-0-sRGB-0-0-0-GLES2_U002c0-512MB-85-220-0-0.png/100x100bb.png",
      "storeUrl": "https://apps.apple.com/jp/app/beersmith-mobile-home-brewing/id640670118?uo=2",
      "price": {
        "amount": 800,
        "currency": "JPY",
        "formatted": "¥800"
      },
      "primaryCategory": {
        "id": "6023",
        "name": "フード／ドリンク"
      },
      "releaseDate": "2013年5月6日"
    },
    {
      "rank": 4,
      "previousRank": 5,
      "rankChange": 1,
      "isNew": false,
      "appleId": "308630840",
      "name": "DreamCocktail",
      "developer": "Dreamonline,inc.",
      "developerUrl": "https://apps.apple.com/jp/developer/dreamonline-inc/id304609787?uo=2",
      "iconUrl": "https://is1-ssl.mzstatic.com/image/thumb/Purple211/v4/e8/e8/5a/e8e85a13-928e-ac3d-f948-6a05548f4db9/AppIcon-1x_U007emarketing-0-7-0-85-220-0.png/100x100bb.png",
      "storeUrl": "https://apps.apple.com/jp/app/dreamcocktail/id308630840?uo=2",
      "price": {
        "amount": 500,
        "currency": "JPY",
        "formatted": "¥500"
      },
      "primaryCategory": {
        "id": "6023",
        "name": "フード／ドリンク"
      },
      "releaseDate": "2009年3月26日"
    },
    {
      "rank": 5,
      "previousRank": 6,
      "rankChange": 1,
      "isNew": false,
      "appleId": "451689948",
      "name": "ワインiQ",
      "developer": "UNITED, Inc.",
      "developerUrl": "https://apps.apple.com/jp/developer/united-inc/id375618440?uo=2",
      "iconUrl": "https://is1-ssl.mzstatic.com/image/thumb/Purple3/v4/22/db/e5/22dbe5c2-7bed-84a0-d5cd-084093630eb9/mzl.yyznapxw.jpg/100x100bb.png",
      "storeUrl": "https://apps.apple.com/jp/app/%E3%83%AF%E3%82%A4%E3%83%B3iq/id451689948?uo=2",
      "price": {
        "amount": 160,
        "currency": "JPY",
        "formatted": "¥160"
      },
      "primaryCategory": {
        "id": "6023",
        "name": "フード／ドリンク"
      },
      "releaseDate": "2011年7月25日"
    },
    {
      "rank": 6,
      "previousRank": 7,
      "rankChange": 1,
      "isNew": false,
      "appleId": "925904165",
      "name": "ワインコレクションPro - ラベル写真の記録アプリ",
      "developer": "MONOPOLEAPPS K.K.",
      "developerUrl": "https://apps.apple.com/jp/developer/monopoleapps-k-k/id925904164?uo=2",
      "iconUrl": "https://is1-ssl.mzstatic.com/image/thumb/Purple211/v4/ea/e7/a0/eae7a099-7f67-5a68-3d57-d432df350210/AppIcon-0-0-1x_U007emarketing-0-8-0-85-220.png/100x100bb.png",
      "storeUrl": "https://apps.apple.com/jp/app/%E3%83%AF%E3%82%A4%E3%83%B3%E3%82%B3%E3%83%AC%E3%82%AF%E3%82%B7%E3%83%A7%E3%83%B3pro-%E3%83%A9%E3%83%99%E3%83%AB%E5%86%99%E7%9C%9F%E3%81%AE%E8%A8%98%E9%8C%B2%E3%82%A2%E3%83%97%E3%83%AA/id925904165?uo=2",
      "price": {
        "amount": 500,
        "currency": "JPY",
        "formatted": "¥500"
      },
      "primaryCategory": {
        "id": "6023",
        "name": "フード／ドリンク"
      },
      "releaseDate": "2014年10月25日"
    },
    {
      "rank": 7,
      "previousRank": 8,
      "rankChange": 1,
      "isNew": false,
      "appleId": "410512631",
      "name": "カクテル手帳",
      "developer": "Ea, Inc.",
      "developerUrl": "https://apps.apple.com/jp/developer/ea-inc/id293212542?uo=2",
      "iconUrl": "https://is1-ssl.mzstatic.com/image/thumb/Purple118/v4/f9/02/dd/f902dd9e-2ddd-2eff-42a6-886d721f39fd/AppIcon-1x_U007emarketing-0-0-GLES2_U002c0-512MB-sRGB-0-0-0-85-220-0-0-0-2.png/100x100bb.png",
      "storeUrl": "https://apps.apple.com/jp/app/%E3%82%AB%E3%82%AF%E3%83%86%E3%83%AB%E6%89%8B%E5%B8%B3/id410512631?uo=2",
      "price": {
        "amount": 500,
        "currency": "JPY",
        "formatted": "¥500"
      },
      "primaryCategory": {
        "id": "6023",
        "name": "フード／ドリンク"
      },
      "releaseDate": "2010年12月22日"
    },
    {
      "rank": 8,
      "previousRank": 9,
      "rankChange": 1,
      "isNew": false,
      "appleId": "408185312",
      "name": "laCook",
      "developer": "nzw31",
      "developerUrl": "https://apps.apple.com/jp/developer/nzw31/id395881681?uo=2",
      "iconUrl": "https://is1-ssl.mzstatic.com/image/thumb/Purple221/v4/dc/56/c5/dc56c545-87f9-3c5d-9a9c-b6395954f884/AppIcon-0-0-1x_U007emarketing-0-3-0-85-220.png/100x100bb.png",
      "storeUrl": "https://apps.apple.com/jp/app/lacook/id408185312?uo=2",
      "price": {
        "amount": 200,
        "currency": "JPY",
        "formatted": "¥200"
      },
      "primaryCategory": {
        "id": "6023",
        "name": "フード／ドリンク"
      },
      "releaseDate": "2010年12月15日"
    },
    {
      "rank": 9,
      "previousRank": 10,
      "rankChange": 1,
      "isNew": false,
      "appleId": "394057312",
      "name": "かいもの職人",
      "developer": "HumanTechnoResearch Co.,Ltd.",
      "developerUrl": "https://apps.apple.com/jp/developer/humantechnoresearch-co-ltd/id394057315?uo=2",
      "iconUrl": "https://is1-ssl.mzstatic.com/image/thumb/Purple/e5/b6/7f/mzl.pfgztuwc.png/100x100bb.png",
      "storeUrl": "https://apps.apple.com/jp/app/%E3%81%8B%E3%81%84%E3%82%82%E3%81%AE%E8%81%B7%E4%BA%BA/id394057312?uo=2",
      "price": {
        "amount": 500,
        "currency": "JPY",
        "formatted": "¥500"
      },
      "primaryCategory": {
        "id": "6023",
        "name": "フード／ドリンク"
      },
      "releaseDate": "2010年9月29日"
    },
    {
      "rank": 10,
      "previousRank": 11,
      "rankChange": 1,
      "isNew": false,
      "appleId": "466252999",
      "name": "ベジタリアンレシピ",
      "developer": "Green Kitchen Stories",
      "developerUrl": "https://apps.apple.com/jp/developer/green-kitchen-stories/id1675330681?uo=2",
      "iconUrl": "https://is1-ssl.mzstatic.com/image/thumb/Purple118/v4/21/79/0d/21790dc9-0c2e-c445-20fe-6e7ef8b82949/AppIcon-0-1x_U007emarketing-0-0-GLES2_U002c0-512MB-sRGB-0-0-0-85-220-0-0-0-6.png/100x100bb.png",
      "storeUrl": "https://apps.apple.com/jp/app/%E3%83%99%E3%82%B8%E3%82%BF%E3%83%AA%E3%82%A2%E3%83%B3%E3%83%AC%E3%82%B7%E3%83%94/id466252999?uo=2",
      "price": {
        "amount": 600,
        "currency": "JPY",
        "formatted": "¥600"
      },
      "primaryCategory": {
        "id": "6023",
        "name": "フード／ドリンク"
      },
      "releaseDate": "2011年10月12日"
    },
    {
      "rank": 11,
      "previousRank": 12,
      "rankChange": 1,
      "isNew": false,
      "appleId": "429132577",
      "name": "お酒の知識",
      "developer": "Li Guo",
      "developerUrl": "https://apps.apple.com/jp/developer/li-guo/id393107253?uo=2",
      "iconUrl": "https://is1-ssl.mzstatic.com/image/thumb/Purple116/v4/0d/21/2f/0d212f4b-961f-2386-91d1-0223753a89fc/AppIcon-0-0-1x_U007emarketing-0-0-0-4-0-0-sRGB-0-0-0-GLES2_U002c0-512MB-85-220-0-0.jpeg/100x100bb.png",
      "storeUrl": "https://apps.apple.com/jp/app/%E3%81%8A%E9%85%92%E3%81%AE%E7%9F%A5%E8%AD%98/id429132577?uo=2",
      "price": {
        "amount": 150,
        "currency": "JPY",
        "formatted": "¥150"
      },
      "primaryCategory": {
        "id": "6023",
        "name": "フード／ドリンク"
      },
      "releaseDate": "2011年4月12日"
    },
    {
      "rank": 12,
      "previousRank": 13,
      "rankChange": 1,
      "isNew": false,
      "appleId": "424573605",
      "name": "日本食品成分ナビ＋レシピ管理",
      "developer": "AOBO Co.,Ltd",
      "developerUrl": "https://apps.apple.com/jp/developer/aobo-co-ltd/id310846199?uo=2",
      "iconUrl": "https://is1-ssl.mzstatic.com/image/thumb/Purple211/v4/cd/ce/76/cdce76e0-bfb9-d754-b663-3e6953b20f37/AppIcon-0-0-1x_U007emarketing-0-11-0-85-220.png/100x100bb.png",
      "storeUrl": "https://apps.apple.com/jp/app/%E6%97%A5%E6%9C%AC%E9%A3%9F%E5%93%81%E6%88%90%E5%88%86%E3%83%8A%E3%83%93-%E3%83%AC%E3%82%B7%E3%83%94%E7%AE%A1%E7%90%86/id424573605?uo=2",
      "price": {
        "amount": 1100,
        "currency": "JPY",
        "formatted": "¥1,100"
      },
      "primaryCategory": {
        "id": "6023",
        "name": "フード／ドリンク"
      },
      "releaseDate": "2011年3月11日"
    },
    {
      "rank": 13,
      "previousRank": 14,
      "rankChange": 1,
      "isNew": false,
      "appleId": "680263335",
      "name": "ショップカード管理",
      "developer": "SHUJI FUKUNAGA",
      "developerUrl": "https://apps.apple.com/jp/developer/shuji-fukunaga/id469076836?uo=2",
      "iconUrl": "https://is1-ssl.mzstatic.com/image/thumb/Purple221/v4/fe/bb/88/febb8816-a4e3-df5a-e560-07cbfddbe34e/AppIcon-0-1x_U007emarketing-0-11-0-85-220-0.png/100x100bb.png",
      "storeUrl": "https://apps.apple.com/jp/app/%E3%82%B7%E3%83%A7%E3%83%83%E3%83%97%E3%82%AB%E3%83%BC%E3%83%89%E7%AE%A1%E7%90%86/id680263335?uo=2",
      "price": {
        "amount": 150,
        "currency": "JPY",
        "formatted": "¥150"
      },
      "primaryCategory": {
        "id": "6023",
        "name": "フード／ドリンク"
      },
      "releaseDate": "2013年8月2日"
    },
    {
      "rank": 14,
      "previousRank": 15,
      "rankChange": 1,
      "isNew": false,
      "appleId": "593857388",
      "name": "健康的なデザート by Green Kitchen",
      "developer": "Green Kitchen Stories",
      "developerUrl": "https://apps.apple.com/jp/developer/green-kitchen-stories/id1675330681?uo=2",
      "iconUrl": "https://is1-ssl.mzstatic.com/image/thumb/Purple19/v4/f2/62/9f/f2629f56-89e9-0229-12f1-a5baad7c3763/mzm.cckzdzfr.png/100x100bb.png",
      "storeUrl": "https://apps.apple.com/jp/app/%E5%81%A5%E5%BA%B7%E7%9A%84%E3%81%AA%E3%83%87%E3%82%B6%E3%83%BC%E3%83%88-by-green-kitchen/id593857388?uo=2",
      "price": {
        "amount": 500,
        "currency": "JPY",
        "formatted": "¥500"
      },
      "primaryCategory": {
        "id": "6023",
        "name": "フード／ドリンク"
      },
      "releaseDate": "2013年2月26日"
    },
    {
      "rank": 15,
      "previousRank": 16,
      "rankChange": 1,
      "isNew": false,
      "appleId": "315514944",
      "name": "实用家常菜谱大全",
      "developer": "Xiaofei Tang",
      "developerUrl": "https://apps.apple.com/jp/developer/xiaofei-tang/id309518546?uo=2",
      "iconUrl": "https://is1-ssl.mzstatic.com/image/thumb/Purple114/v4/76/ac/76/76ac7672-bbc5-cffd-fb1a-21ddb2940c5f/AppIcon-1x_U007emarketing-0-10-0-85-220.png/100x100bb.png",
      "storeUrl": "https://apps.apple.com/jp/app/%E5%AE%9E%E7%94%A8%E5%AE%B6%E5%B8%B8%E8%8F%9C%E8%B0%B1%E5%A4%A7%E5%85%A8/id315514944?uo=2",
      "price": {
        "amount": 150,
        "currency": "JPY",
        "formatted": "¥150"
      },
      "primaryCategory": {
        "id": "6023",
        "name": "フード／ドリンク"
      },
      "releaseDate": "2009年5月13日"
    },
    {
      "rank": 16,
      "previousRank": 17,
      "rankChange": 1,
      "isNew": false,
      "appleId": "327068055",
      "name": "Wine Vintages: ワインのヴィンテージ",
      "developer": "VinoMobile",
      "developerUrl": "https://apps.apple.com/jp/developer/vinomobile/id314951226?uo=2",
      "iconUrl": "https://is1-ssl.mzstatic.com/image/thumb/Purple221/v4/4a/e0/89/4ae089a8-2aa6-64cd-d8d2-ce5179d33767/AppIcon-0-0-1x_U007epad-0-1-0-85-220.png/100x100bb.png",
      "storeUrl": "https://apps.apple.com/jp/app/wine-vintages-%E3%83%AF%E3%82%A4%E3%83%B3%E3%81%AE%E3%83%B4%E3%82%A3%E3%83%B3%E3%83%86%E3%83%BC%E3%82%B8/id327068055?uo=2",
      "price": {
        "amount": 500,
        "currency": "JPY",
        "formatted": "¥500"
      },
      "primaryCategory": {
        "id": "6023",
        "name": "フード／ドリンク"
      },
      "releaseDate": "2009年8月22日"
    },
    {
      "rank": 17,
      "previousRank": 18,
      "rankChange": 1,
      "isNew": false,
      "appleId": "534220544",
      "name": "The Great Coffee App",
      "developer": "Baglan Dosmagambetov",
      "developerUrl": "https://apps.apple.com/jp/developer/baglan-dosmagambetov/id429890736?uo=2",
      "iconUrl": "https://is1-ssl.mzstatic.com/image/thumb/Purple124/v4/01/69/0b/01690bcc-2a50-dd57-c942-09a2a3a908d8/AppIcon-0-0-1x_U007emarketing-0-0-0-10-0-0-sRGB-0-0-0-GLES2_U002c0-512MB-85-220-0-0.png/100x100bb.png",
      "storeUrl": "https://apps.apple.com/jp/app/the-great-coffee-app/id534220544?uo=2",
      "price": {
        "amount": 500,
        "currency": "JPY",
        "formatted": "¥500"
      },
      "primaryCategory": {
        "id": "6023",
        "name": "フード／ドリンク"
      },
      "releaseDate": "2012年9月23日"
    },
    {
      "rank": 18,
      "previousRank": 19,
      "rankChange": 1,
      "isNew": false,
      "appleId": "284447372",
      "name": "BigTipper™",
      "developer": "PureBlend Software",
      "developerUrl": "https://apps.apple.com/jp/developer/pureblend-software/id284447375?uo=2",
      "iconUrl": "https://is1-ssl.mzstatic.com/image/thumb/Purple211/v4/11/91/5f/11915fa5-0fde-843f-aec9-fe701c95a558/AppIcon-0-0-1x_U007emarketing-0-8-0-0-85-220.png/100x100bb.png",
      "storeUrl": "https://apps.apple.com/jp/app/bigtipper/id284447372?uo=2",
      "price": {
        "amount": 300,
        "currency": "JPY",
        "formatted": "¥300"
      },
      "primaryCategory": {
        "id": "6023",
        "name": "フード／ドリンク"
      },
      "releaseDate": "2019年2月12日"
    },
    {
      "rank": 19,
      "previousRank": 20,
      "rankChange": 1,
      "isNew": false,
      "appleId": "1554847613",
      "name": "Split 割り勘",
      "developer": "Shinji Nishijima",
      "developerUrl": "https://apps.apple.com/jp/developer/shinji-nishijima/id1554847615?uo=2",
      "iconUrl": "https://is1-ssl.mzstatic.com/image/thumb/Purple211/v4/b6/4d/e5/b64de54f-185e-d1bf-ab06-7a8f154ef45a/Split-0-0-1x_U007ephone-0-1-85-220.png/100x100bb.png",
      "storeUrl": "https://apps.apple.com/jp/app/split-%E5%89%B2%E3%82%8A%E5%8B%98/id1554847613?uo=2",
      "price": {
        "amount": 150,
        "currency": "JPY",
        "formatted": "¥150"
      },
      "primaryCategory": {
        "id": "6023",
        "name": "フード／ドリンク"
      },
      "releaseDate": "2021年2月28日"
    },
    {
      "rank": 20,
      "previousRank": 21,
      "rankChange": 1,
      "isNew": false,
      "appleId": "955856112",
      "name": "自分レシピ",
      "developer": "masashi012",
      "developerUrl": "https://apps.apple.com/jp/developer/masashi012/id524897474?uo=2",
      "iconUrl": "https://is1-ssl.mzstatic.com/image/thumb/Purple126/v4/65/7e/de/657eded7-02ae-7fbb-9117-df5a8f84a5e5/AppIcon-1x_U007emarketing-0-6-0-85-220.png/100x100bb.png",
      "storeUrl": "https://apps.apple.com/jp/app/%E8%87%AA%E5%88%86%E3%83%AC%E3%82%B7%E3%83%94/id955856112?uo=2",
      "price": {
        "amount": 600,
        "currency": "JPY",
        "formatted": "¥600"
      },
      "primaryCategory": {
        "id": "6023",
        "name": "フード／ドリンク"
      },
      "releaseDate": "2015年1月28日"
    },
    {
      "rank": 21,
      "previousRank": 22,
      "rankChange": 1,
      "isNew": false,
      "appleId": "552821843",
      "name": "Wine Maps",
      "developer": "Jonathan Lord",
      "developerUrl": "https://apps.apple.com/jp/developer/jonathan-lord/id517523156?uo=2",
      "iconUrl": "https://is1-ssl.mzstatic.com/image/thumb/Purple221/v4/22/a1/fb/22a1fb63-3403-e4ee-c739-671503920c8f/AppIcon-0-1x_U007emarketing-0-8-0-85-220-0.png/100x100bb.png",
      "storeUrl": "https://apps.apple.com/jp/app/wine-maps/id552821843?uo=2",
      "price": {
        "amount": 150,
        "currency": "JPY",
        "formatted": "¥150"
      },
      "primaryCategory": {
        "id": "6023",
        "name": "フード／ドリンク"
      },
      "releaseDate": "2012年8月27日"
    },
    {
      "rank": 22,
      "previousRank": 23,
      "rankChange": 1,
      "isNew": false,
      "appleId": "6443524001",
      "name": "ベターホームの糖尿病予防献立",
      "developer": "Better Home Association",
      "developerUrl": "https://apps.apple.com/jp/developer/better-home-association/id1639035730?uo=2",
      "iconUrl": "https://is1-ssl.mzstatic.com/image/thumb/Purple122/v4/4a/a0/f6/4aa0f61b-72c6-e293-4d23-6791c2938973/AppIcon-0-0-1x_U007emarketing-0-0-0-10-0-0-sRGB-0-0-0-GLES2_U002c0-512MB-85-220-0-0.png/100x100bb.png",
      "storeUrl": "https://apps.apple.com/jp/app/%E3%83%99%E3%82%BF%E3%83%BC%E3%83%9B%E3%83%BC%E3%83%A0%E3%81%AE%E7%B3%96%E5%B0%BF%E7%97%85%E4%BA%88%E9%98%B2%E7%8C%AE%E7%AB%8B/id6443524001?uo=2",
      "price": {
        "amount": 300,
        "currency": "JPY",
        "formatted": "¥300"
      },
      "primaryCategory": {
        "id": "6023",
        "name": "フード／ドリンク"
      },
      "releaseDate": "2022年10月14日"
    },
    {
      "rank": 23,
      "previousRank": 24,
      "rankChange": 1,
      "isNew": false,
      "appleId": "1079607960",
      "name": "Oh She Glows",
      "developer": "Glo Bakery Corporation",
      "developerUrl": "https://apps.apple.com/jp/developer/glo-bakery-corporation/id1079607959?uo=2",
      "iconUrl": "https://is1-ssl.mzstatic.com/image/thumb/Purple211/v4/7e/a7/99/7ea79959-4177-5107-fa78-25d5b90dd5af/AppIcon-0-0-1x_U007emarketing-0-8-0-0-0-85-220.png/100x100bb.png",
      "storeUrl": "https://apps.apple.com/jp/app/oh-she-glows/id1079607960?uo=2",
      "price": {
        "amount": 500,
        "currency": "JPY",
        "formatted": "¥500"
      },
      "primaryCategory": {
        "id": "6023",
        "name": "フード／ドリンク"
      },
      "releaseDate": "2016年4月10日"
    },
    {
      "rank": 24,
      "previousRank": 25,
      "rankChange": 1,
      "isNew": false,
      "appleId": "298883838",
      "name": "Fromage",
      "developer": "Steve Welch",
      "developerUrl": "https://apps.apple.com/jp/developer/steve-welch/id298883841?uo=2",
      "iconUrl": "https://is1-ssl.mzstatic.com/image/thumb/Purple116/v4/b3/73/50/b37350b1-3911-a5f4-0025-78d2cf08f24b/AppIcon-0-0-1x_U007emarketing-0-0-0-9-0-0-sRGB-0-0-0-GLES2_U002c0-512MB-85-220-0-0.png/100x100bb.png",
      "storeUrl": "https://apps.apple.com/jp/app/fromage/id298883838?uo=2",
      "price": {
        "amount": 600,
        "currency": "JPY",
        "formatted": "¥600"
      },
      "primaryCategory": {
        "id": "6023",
        "name": "フード／ドリンク"
      },
      "releaseDate": "2008年12月4日"
    },
    {
      "rank": 25,
      "previousRank": 26,
      "rankChange": 1,
      "isNew": false,
      "appleId": "980368562",
      "name": "FitMenCook - Healthy Recipes",
      "developer": "Nibble Apps Ltd",
      "developerUrl": "https://apps.apple.com/jp/developer/nibble-apps-ltd/id900888256?uo=2",
      "iconUrl": "https://is1-ssl.mzstatic.com/image/thumb/Purple211/v4/76/9c/1e/769c1ee1-a743-6116-4c9b-e3a368958670/AppIcon-0-0-1x_U007emarketing-0-7-0-85-220.png/100x100bb.png",
      "storeUrl": "https://apps.apple.com/jp/app/fitmencook-healthy-recipes/id980368562?uo=2",
      "price": {
        "amount": 600,
        "currency": "JPY",
        "formatted": "¥600"
      },
      "primaryCategory": {
        "id": "6023",
        "name": "フード／ドリンク"
      },
      "releaseDate": "2015年5月12日"
    },
    {
      "rank": 26,
      "previousRank": 27,
      "rankChange": 1,
      "isNew": false,
      "appleId": "1522257876",
      "name": "ワインノート",
      "developer": "Tomohiro Sasaki",
      "developerUrl": "https://apps.apple.com/jp/developer/tomohiro-sasaki/id1291219090?uo=2",
      "iconUrl": "https://is1-ssl.mzstatic.com/image/thumb/Purple221/v4/26/46/e0/2646e070-9ea7-12ba-5d19-ef7c6cd40f7a/AppIcon-0-0-1x_U007emarketing-0-7-0-85-220.png/100x100bb.png",
      "storeUrl": "https://apps.apple.com/jp/app/%E3%83%AF%E3%82%A4%E3%83%B3%E3%83%8E%E3%83%BC%E3%83%88/id1522257876?uo=2",
      "price": {
        "amount": 300,
        "currency": "JPY",
        "formatted": "¥300"
      },
      "primaryCategory": {
        "id": "6023",
        "name": "フード／ドリンク"
      },
      "releaseDate": "2020年7月9日"
    },
    {
      "rank": 27,
      "previousRank": 28,
      "rankChange": 1,
      "isNew": false,
      "appleId": "286574416",
      "name": "iBartender Cocktail Recipes",
      "developer": "Kevin Kozan",
      "developerUrl": "https://apps.apple.com/jp/developer/kevin-kozan/id283730007?uo=2",
      "iconUrl": "https://is1-ssl.mzstatic.com/image/thumb/Purple211/v4/f6/96/30/f696307b-ac00-a65e-3985-22b7737ea74e/AppIcon-1x_U007emarketing-0-5-85-220-0.png/100x100bb.png",
      "storeUrl": "https://apps.apple.com/jp/app/ibartender-cocktail-recipes/id286574416?uo=2",
      "price": {
        "amount": 150,
        "currency": "JPY",
        "formatted": "¥150"
      },
      "primaryCategory": {
        "id": "6023",
        "name": "フード／ドリンク"
      },
      "releaseDate": "2019年2月12日"
    },
    {
      "rank": 28,
      "previousRank": 29,
      "rankChange": 1,
      "isNew": false,
      "appleId": "418365881",
      "name": "Starbucks Pocket Coffee Master",
      "developer": "Mark David",
      "developerUrl": "https://apps.apple.com/jp/developer/mark-david/id328738635?uo=2",
      "iconUrl": "https://is1-ssl.mzstatic.com/image/thumb/Purple5/v4/15/90/db/1590db0b-eb12-7c28-0737-9bcb832e6028/mzl.jdquxzkx.png/100x100bb.png",
      "storeUrl": "https://apps.apple.com/jp/app/starbucks-pocket-coffee-master/id418365881?uo=2",
      "price": {
        "amount": 150,
        "currency": "JPY",
        "formatted": "¥150"
      },
      "primaryCategory": {
        "id": "6023",
        "name": "フード／ドリンク"
      },
      "releaseDate": "2011年3月27日"
    },
    {
      "rank": 29,
      "previousRank": 30,
      "rankChange": 1,
      "isNew": false,
      "appleId": "287917148",
      "name": "食品添加物 2",
      "developer": "IGRASS PTY LTD",
      "developerUrl": "https://apps.apple.com/jp/developer/igrass-pty-ltd/id287917151?uo=2",
      "iconUrl": "https://is1-ssl.mzstatic.com/image/thumb/Purple126/v4/52/0e/25/520e25c5-de52-2225-420c-7e67ddef6238/AppIcon-0-0-1x_U007emarketing-0-0-0-7-0-0-sRGB-0-0-0-GLES2_U002c0-512MB-85-220-0-0.png/100x100bb.png",
      "storeUrl": "https://apps.apple.com/jp/app/%E9%A3%9F%E5%93%81%E6%B7%BB%E5%8A%A0%E7%89%A9-2/id287917148?uo=2",
      "price": {
        "amount": 500,
        "currency": "JPY",
        "formatted": "¥500"
      },
      "primaryCategory": {
        "id": "6023",
        "name": "フード／ドリンク"
      },
      "releaseDate": "2019年2月1日"
    },
    {
      "rank": 30,
      "previousRank": 31,
      "rankChange": 1,
      "isNew": false,
      "appleId": "478652543",
      "name": "Go Tip – Simple Tip Calculator",
      "developer": "Love 4 Apps, LLC",
      "developerUrl": "https://apps.apple.com/jp/developer/love-4-apps-llc/id1659106334?uo=2",
      "iconUrl": "https://is1-ssl.mzstatic.com/image/thumb/Purple221/v4/b8/b9/15/b8b91571-aabc-bda4-90fc-d6423ab07cc6/AppIcon-0-0-1x_U007epad-0-1-0-85-220.jpeg/100x100bb.png",
      "storeUrl": "https://apps.apple.com/jp/app/go-tip-simple-tip-calculator/id478652543?uo=2",
      "price": {
        "amount": 50,
        "currency": "JPY",
        "formatted": "¥50"
      },
      "primaryCategory": {
        "id": "6023",
        "name": "フード／ドリンク"
      },
      "releaseDate": "2011年12月14日"
    },
    {
      "rank": 31,
      "previousRank": 32,
      "rankChange": 1,
      "isNew": false,
      "appleId": "1505065609",
      "name": "Love, Manuela",
      "developer": "Passion For Baking AS",
      "developerUrl": "https://apps.apple.com/jp/developer/passion-for-baking-as/id1505065608?uo=2",
      "iconUrl": "https://is1-ssl.mzstatic.com/image/thumb/Purple211/v4/03/76/fd/0376fddd-bb34-fe2c-0a73-f0e6fad68cb8/AppIcon-0-0-1x_U007emarketing-0-8-0-85-220.png/100x100bb.png",
      "storeUrl": "https://apps.apple.com/jp/app/love-manuela/id1505065609?uo=2",
      "price": {
        "amount": 2000,
        "currency": "JPY",
        "formatted": "¥2,000"
      },
      "primaryCategory": {
        "id": "6023",
        "name": "フード／ドリンク"
      },
      "releaseDate": "2020年4月22日"
    },
    {
      "rank": 32,
      "previousRank": 33,
      "rankChange": 1,
      "isNew": false,
      "appleId": "477957929",
      "name": "Enogea Barolo docg Map",
      "developer": "Alessandro Masnaghetti Editore",
      "developerUrl": "https://apps.apple.com/jp/developer/alessandro-masnaghetti-editore/id428841671?uo=2",
      "iconUrl": "https://is1-ssl.mzstatic.com/image/thumb/Purple113/v4/e7/2e/0b/e72e0bd4-1872-2d41-61bc-b5056d04cdbb/AppIcon-1x_U007emarketing-0-8-0-0-85-220.png/100x100bb.png",
      "storeUrl": "https://apps.apple.com/jp/app/enogea-barolo-docg-map/id477957929?uo=2",
      "price": {
        "amount": 1500,
        "currency": "JPY",
        "formatted": "¥1,500"
      },
      "primaryCategory": {
        "id": "6023",
        "name": "フード／ドリンク"
      },
      "releaseDate": "2011年11月11日"
    },
    {
      "rank": 33,
      "previousRank": 34,
      "rankChange": 1,
      "isNew": false,
      "appleId": "316131048",
      "name": "Kitchen Calculator PRO",
      "developer": "Juan Baurin",
      "developerUrl": "https://apps.apple.com/jp/developer/juan-baurin/id1542536957?uo=2",
      "iconUrl": "https://is1-ssl.mzstatic.com/image/thumb/Purple211/v4/0c/16/06/0c16061f-1e76-db69-1fbd-2cc91fb85c07/AppIconPro-0-0-1x_U007emarketing-0-8-0-85-220.png/100x100bb.png",
      "storeUrl": "https://apps.apple.com/jp/app/kitchen-calculator-pro/id316131048?uo=2",
      "price": {
        "amount": 500,
        "currency": "JPY",
        "formatted": "¥500"
      },
      "primaryCategory": {
        "id": "6023",
        "name": "フード／ドリンク"
      },
      "releaseDate": "2009年6月7日"
    },
    {
      "rank": 34,
      "previousRank": 35,
      "rankChange": 1,
      "isNew": false,
      "appleId": "1587044301",
      "name": "Cook Units",
      "developer": "Didier Burton",
      "developerUrl": "https://apps.apple.com/jp/developer/didier-burton/id1514037982?uo=2",
      "iconUrl": "https://is1-ssl.mzstatic.com/image/thumb/Purple211/v4/df/f2/dc/dff2dcb7-3b7e-92d3-ec2d-ebe953308ffc/CookUnitsIcon-0-0-1x_U007epad-0-0-0-1-0-sRGB-85-220.png/100x100bb.png",
      "storeUrl": "https://apps.apple.com/jp/app/cook-units/id1587044301?uo=2",
      "price": {
        "amount": 150,
        "currency": "JPY",
        "formatted": "¥150"
      },
      "primaryCategory": {
        "id": "6023",
        "name": "フード／ドリンク"
      },
      "releaseDate": "2021年10月19日"
    },
    {
      "rank": 35,
      "previousRank": 36,
      "rankChange": 1,
      "isNew": false,
      "appleId": "527031134",
      "name": "Catador Cupping",
      "developer": "Softlogic, S.A.",
      "developerUrl": "https://apps.apple.com/jp/developer/softlogic-s-a/id1635350915?uo=2",
      "iconUrl": "https://is1-ssl.mzstatic.com/image/thumb/Purple126/v4/35/a5/c9/35a5c9d6-6fa0-2703-31f4-c152323b26aa/AppIcon-0-0-1x_U007emarketing-0-0-0-7-0-0-sRGB-0-0-0-GLES2_U002c0-512MB-85-220-0-0.png/100x100bb.png",
      "storeUrl": "https://apps.apple.com/jp/app/catador-cupping/id527031134?uo=2",
      "price": {
        "amount": 2500,
        "currency": "JPY",
        "formatted": "¥2,500"
      },
      "primaryCategory": {
        "id": "6023",
        "name": "フード／ドリンク"
      },
      "releaseDate": "2012年5月22日"
    },
    {
      "rank": 36,
      "previousRank": 37,
      "rankChange": 1,
      "isNew": false,
      "appleId": "602496538",
      "name": "AeroPress Timer",
      "developer": "Beloved Robot, LLC",
      "developerUrl": "https://apps.apple.com/jp/developer/beloved-robot-llc/id602496541?uo=2",
      "iconUrl": "https://is1-ssl.mzstatic.com/image/thumb/Purple124/v4/c9/bb/57/c9bb570e-3c18-3ef1-64c2-08ec3da9819d/AppIcon-0-1x_U007emarketing-0-0-GLES2_U002c0-512MB-sRGB-0-0-0-85-220-0-0-0-5.png/100x100bb.png",
      "storeUrl": "https://apps.apple.com/jp/app/aeropress-timer/id602496538?uo=2",
      "price": {
        "amount": 800,
        "currency": "JPY",
        "formatted": "¥800"
      },
      "primaryCategory": {
        "id": "6023",
        "name": "フード／ドリンク"
      },
      "releaseDate": "2013年3月6日"
    },
    {
      "rank": 37,
      "previousRank": 38,
      "rankChange": 1,
      "isNew": false,
      "appleId": "396836856",
      "name": "Nutrients - Nutrition Facts",
      "developer": "Pomegranate Apps LLC",
      "developerUrl": "https://apps.apple.com/jp/developer/pomegranate-apps-llc/id293619496?uo=2",
      "iconUrl": "https://is1-ssl.mzstatic.com/image/thumb/Purple116/v4/b4/10/39/b4103942-e201-aa77-1e99-92429fe48ae9/Nutrients_Icon-0-1x_U007emarketing-0-10-0-85-220.jpeg/100x100bb.png",
      "storeUrl": "https://apps.apple.com/jp/app/nutrients-nutrition-facts/id396836856?uo=2",
      "price": {
        "amount": 800,
        "currency": "JPY",
        "formatted": "¥800"
      },
      "primaryCategory": {
        "id": "6023",
        "name": "フード／ドリンク"
      },
      "releaseDate": "2010年10月27日"
    },
    {
      "rank": 38,
      "previousRank": 39,
      "rankChange": 1,
      "isNew": false,
      "appleId": "1515266167",
      "name": "My Mini Menu",
      "developer": "Oliver Shingler",
      "developerUrl": "https://apps.apple.com/jp/developer/oliver-shingler/id886565740?uo=2",
      "iconUrl": "https://is1-ssl.mzstatic.com/image/thumb/Purple211/v4/77/d0/d6/77d0d626-8227-9e31-4848-37d6c47c4e88/AppIcon-1x_U007emarketing-0-7-0-85-220-0.png/100x100bb.png",
      "storeUrl": "https://apps.apple.com/jp/app/my-mini-menu/id1515266167?uo=2",
      "price": {
        "amount": 150,
        "currency": "JPY",
        "formatted": "¥150"
      },
      "primaryCategory": {
        "id": "6023",
        "name": "フード／ドリンク"
      },
      "releaseDate": "2020年7月8日"
    },
    {
      "rank": 39,
      "previousRank": 40,
      "rankChange": 1,
      "isNew": false,
      "appleId": "481015676",
      "name": "YogicFoods",
      "developer": "Gary Saggu",
      "developerUrl": "https://apps.apple.com/jp/developer/gary-saggu/id465733546?uo=2",
      "iconUrl": "https://is1-ssl.mzstatic.com/image/thumb/Purple126/v4/e9/5c/0c/e95c0c07-f38d-f8bb-9d3a-93e579de806d/AppIcon-1x_U007emarketing-0-5-0-85-220.png/100x100bb.png",
      "storeUrl": "https://apps.apple.com/jp/app/yogicfoods/id481015676?uo=2",
      "price": {
        "amount": 600,
        "currency": "JPY",
        "formatted": "¥600"
      },
      "primaryCategory": {
        "id": "6023",
        "name": "フード／ドリンク"
      },
      "releaseDate": "2012年3月26日"
    },
    {
      "rank": 40,
      "previousRank": 41,
      "rankChange": 1,
      "isNew": false,
      "appleId": "898723944",
      "name": "拡大鏡 + フラッシュライト (Torch)",
      "developer": "RV AppStudios LLC",
      "developerUrl": "https://apps.apple.com/jp/developer/rv-appstudios-llc/id340181308?uo=2",
      "iconUrl": "https://is1-ssl.mzstatic.com/image/thumb/Purple221/v4/d4/08/0b/d4080b40-da88-8ea9-d8fa-f39ad67571a1/AppIcon-2-0-0-1x_U007emarketing-0-5-0-85-220.png/100x100bb.png",
      "storeUrl": "https://apps.apple.com/jp/app/%E6%8B%A1%E5%A4%A7%E9%8F%A1-%E3%83%95%E3%83%A9%E3%83%83%E3%82%B7%E3%83%A5%E3%83%A9%E3%82%A4%E3%83%88-torch/id898723944?uo=2",
      "price": {
        "amount": 300,
        "currency": "JPY",
        "formatted": "¥300"
      },
      "primaryCategory": {
        "id": "6023",
        "name": "フード／ドリンク"
      },
      "releaseDate": "2014年7月23日"
    },
    {
      "rank": 41,
      "previousRank": 42,
      "rankChange": 1,
      "isNew": false,
      "appleId": "521577043",
      "name": "Vinocell – Wine cellar manager",
      "developer": "VinoDev",
      "developerUrl": "https://apps.apple.com/jp/developer/vinodev/id319498720?uo=2",
      "iconUrl": "https://is1-ssl.mzstatic.com/image/thumb/Purple221/v4/35/46/92/35469244-05c0-58d7-1c40-cbbdad490443/AppIcon-0-0-1x_U007emarketing-0-7-0-85-220.png/100x100bb.png",
      "storeUrl": "https://apps.apple.com/jp/app/vinocell-wine-cellar-manager/id521577043?uo=2",
      "price": {
        "amount": 1500,
        "currency": "JPY",
        "formatted": "¥1,500"
      },
      "primaryCategory": {
        "id": "6023",
        "name": "フード／ドリンク"
      },
      "releaseDate": "2012年6月5日"
    },
    {
      "rank": 42,
      "previousRank": 43,
      "rankChange": 1,
      "isNew": false,
      "appleId": "301676912",
      "name": "Kitchen Calculator",
      "developer": "Juan Baurin",
      "developerUrl": "https://apps.apple.com/jp/developer/juan-baurin/id1542536957?uo=2",
      "iconUrl": "https://is1-ssl.mzstatic.com/image/thumb/Purple221/v4/23/8e/f8/238ef85a-1fc9-26c3-fd2d-419a205dab28/AppIconStandard-0-0-1x_U007emarketing-0-8-0-85-220.png/100x100bb.png",
      "storeUrl": "https://apps.apple.com/jp/app/kitchen-calculator/id301676912?uo=2",
      "price": {
        "amount": 300,
        "currency": "JPY",
        "formatted": "¥300"
      },
      "primaryCategory": {
        "id": "6023",
        "name": "フード／ドリンク"
      },
      "releaseDate": "2009年1月19日"
    },
    {
      "rank": 43,
      "previousRank": 44,
      "rankChange": 1,
      "isNew": false,
      "appleId": "339739777",
      "name": "iRecipeBook",
      "developer": "Shooby Ban",
      "developerUrl": "https://apps.apple.com/jp/developer/shooby-ban/id289283632?uo=2",
      "iconUrl": "https://is1-ssl.mzstatic.com/image/thumb/Purple6/v4/0e/79/2d/0e792d86-f6ab-ce2c-5955-7b786cf8b6b1/mzl.vyjvxsdw.png/100x100bb.png",
      "storeUrl": "https://apps.apple.com/jp/app/irecipebook/id339739777?uo=2",
      "price": {
        "amount": 150,
        "currency": "JPY",
        "formatted": "¥150"
      },
      "primaryCategory": {
        "id": "6023",
        "name": "フード／ドリンク"
      },
      "releaseDate": "2009年11月24日"
    },
    {
      "rank": 44,
      "previousRank": 45,
      "rankChange": 1,
      "isNew": false,
      "appleId": "1423585518",
      "name": "Roman: budget weight loss",
      "developer": "Roman Kuryanov",
      "developerUrl": "https://apps.apple.com/jp/developer/roman-kuryanov/id1418497651?uo=2",
      "iconUrl": "https://is1-ssl.mzstatic.com/image/thumb/Purple221/v4/0c/5f/99/0c5f9950-68db-c500-0710-0ef2c7ba8a72/AppIcon-0-0-1x_U007epad-0-1-0-sRGB-85-220.png/100x100bb.png",
      "storeUrl": "https://apps.apple.com/jp/app/roman-budget-weight-loss/id1423585518?uo=2",
      "price": {
        "amount": 50,
        "currency": "JPY",
        "formatted": "¥50"
      },
      "primaryCategory": {
        "id": "6023",
        "name": "フード／ドリンク"
      },
      "releaseDate": "2018年8月14日"
    },
    {
      "rank": 45,
      "previousRank": 4,
      "rankChange": -41,
      "isNew": false,
      "appleId": "1550697095",
      "name": "うどん店",
      "developer": "WalterAlex",
      "developerUrl": "https://apps.apple.com/jp/developer/walteralex/id552641993?uo=2",
      "iconUrl": "https://is1-ssl.mzstatic.com/image/thumb/Purple211/v4/08/5b/95/085b9544-930e-9d7e-93fe-31c8c4290a87/AppIcon-0-0-1x_U007emarketing-0-8-0-85-220.png/100x100bb.png",
      "storeUrl": "https://apps.apple.com/jp/app/%E3%81%86%E3%81%A9%E3%82%93%E5%BA%97/id1550697095?uo=2",
      "price": {
        "amount": 300,
        "currency": "JPY",
        "formatted": "¥300"
      },
      "primaryCategory": {
        "id": "6023",
        "name": "フード／ドリンク"
      },
      "releaseDate": "2021年9月13日"
    },
    {
      "rank": 46,
      "previousRank": 46,
      "rankChange": 0,
      "isNew": false,
      "appleId": "502803489",
      "name": "美食杰VIP-视频菜谱大全",
      "developer": "Beijing MeiShiJie Information Technology Co.,Ltd.",
      "developerUrl": "https://apps.apple.com/jp/developer/beijing-meishijie-information-technology-co-ltd/id399239829?uo=2",
      "iconUrl": "https://is1-ssl.mzstatic.com/image/thumb/Purple211/v4/72/91/d4/7291d49e-cda3-3275-213a-dc65fc764764/AppIcon-0-0-1x_U007emarketing-0-8-0-0-85-220.png/100x100bb.png",
      "storeUrl": "https://apps.apple.com/jp/app/%E7%BE%8E%E9%A3%9F%E6%9D%B0vip-%E8%A7%86%E9%A2%91%E8%8F%9C%E8%B0%B1%E5%A4%A7%E5%85%A8/id502803489?uo=2",
      "price": {
        "amount": 150,
        "currency": "JPY",
        "formatted": "¥150"
      },
      "primaryCategory": {
        "id": "6023",
        "name": "フード／ドリンク"
      },
      "releaseDate": "2012年2月28日"
    },
    {
      "rank": 47,
      "previousRank": 47,
      "rankChange": 0,
      "isNew": false,
      "appleId": "813187935",
      "name": "週間のメニュー - あなたの個人的なレシピ本であなたの料理を計画 - iPhone Edition",
      "developer": "Organize Tech Labs AB",
      "developerUrl": "https://apps.apple.com/jp/developer/organize-tech-labs-ab/id580608579?uo=2",
      "iconUrl": "https://is1-ssl.mzstatic.com/image/thumb/Purple3/v4/0e/d7/ac/0ed7accc-da3b-52b2-ec20-7fd2d2ba44a0/pr_source.jpg/100x100bb.png",
      "storeUrl": "https://apps.apple.com/jp/app/%E9%80%B1%E9%96%93%E3%81%AE%E3%83%A1%E3%83%8B%E3%83%A5%E3%83%BC-%E3%81%82%E3%81%AA%E3%81%9F%E3%81%AE%E5%80%8B%E4%BA%BA%E7%9A%84%E3%81%AA%E3%83%AC%E3%82%B7%E3%83%94%E6%9C%AC%E3%81%A7%E3%81%82%E3%81%AA%E3%81%9F%E3%81%AE%E6%96%99%E7%90%86%E3%82%92%E8%A8%88%E7%94%BB-iphone-edition/id813187935?uo=2",
      "price": {
        "amount": 500,
        "currency": "JPY",
        "formatted": "¥500"
      },
      "primaryCategory": {
        "id": "6023",
        "name": "フード／ドリンク"
      },
      "releaseDate": "2014年4月16日"
    },
    {
      "rank": 48,
      "previousRank": 48,
      "rankChange": 0,
      "isNew": false,
      "appleId": "410599593",
      "name": "Jason Vale’s 7-Day Juice Diet",
      "developer": "Juice Master",
      "developerUrl": "https://apps.apple.com/jp/developer/juice-master/id493242642?uo=2",
      "iconUrl": "https://is1-ssl.mzstatic.com/image/thumb/Purple122/v4/a0/f1/bb/a0f1bb0c-70ef-5439-d6a8-2eef8a94adb9/AppIcon-0-0-1x_U007emarketing-0-0-0-7-0-0-sRGB-0-0-0-GLES2_U002c0-512MB-85-220-0-0.png/100x100bb.png",
      "storeUrl": "https://apps.apple.com/jp/app/jason-vales-7-day-juice-diet/id410599593?uo=2",
      "price": {
        "amount": 1100,
        "currency": "JPY",
        "formatted": "¥1,100"
      },
      "primaryCategory": {
        "id": "6023",
        "name": "フード／ドリンク"
      },
      "releaseDate": "2011年1月4日"
    },
    {
      "rank": 49,
      "previousRank": 49,
      "rankChange": 0,
      "isNew": false,
      "appleId": "1132206436",
      "name": "Tim Hortons!!",
      "developer": "Cedric Deschenes",
      "developerUrl": "https://apps.apple.com/jp/developer/cedric-deschenes/id534554140?uo=2",
      "iconUrl": "https://is1-ssl.mzstatic.com/image/thumb/Purple60/v4/9a/5d/6b/9a5d6bd9-fc65-6daf-908e-cad3160597ed/pr_source.jpg/100x100bb.png",
      "storeUrl": "https://apps.apple.com/jp/app/tim-hortons/id1132206436?uo=2",
      "price": {
        "amount": 1500,
        "currency": "JPY",
        "formatted": "¥1,500"
      },
      "primaryCategory": {
        "id": "6023",
        "name": "フード／ドリンク"
      },
      "releaseDate": "2016年7月8日"
    },
    {
      "rank": 50,
      "previousRank": 50,
      "rankChange": 0,
      "isNew": false,
      "appleId": "968492836",
      "name": "PDT Cocktails",
      "developer": "Doudoroff LLC",
      "developerUrl": "https://apps.apple.com/jp/developer/doudoroff-llc/id404082951?uo=2",
      "iconUrl": "https://is1-ssl.mzstatic.com/image/thumb/Purple122/v4/ed/82/22/ed8222e0-f9df-b092-ad83-60aafc343785/AppIcon-pdt-0-0-1x_U007emarketing-0-0-0-7-0-0-sRGB-0-0-0-GLES2_U002c0-512MB-85-220-0-0.png/100x100bb.png",
      "storeUrl": "https://apps.apple.com/jp/app/pdt-cocktails/id968492836?uo=2",
      "price": {
        "amount": 1500,
        "currency": "JPY",
        "formatted": "¥1,500"
      },
      "primaryCategory": {
        "id": "6023",
        "name": "フード／ドリンク"
      },
      "releaseDate": "2015年3月11日"
    },
    {
      "rank": 51,
      "previousRank": 51,
      "rankChange": 0,
      "isNew": false,
      "appleId": "1016450821",
      "name": "VST CoffeeTools PRO for iPhone",
      "developer": "VST",
      "developerUrl": "https://apps.apple.com/jp/developer/vst/id351660250?uo=2",
      "iconUrl": "https://is1-ssl.mzstatic.com/image/thumb/Purple126/v4/3d/b9/c0/3db9c04e-3d03-f809-faa0-2e7b35c24730/AppIcon-0-1x_U007emarketing-0-6-0-85-220.png/100x100bb.png",
      "storeUrl": "https://apps.apple.com/jp/app/vst-coffeetools-pro-for-iphone/id1016450821?uo=2",
      "price": {
        "amount": 6000,
        "currency": "JPY",
        "formatted": "¥6,000"
      },
      "primaryCategory": {
        "id": "6023",
        "name": "フード／ドリンク"
      },
      "releaseDate": "2015年12月18日"
    },
    {
      "rank": 52,
      "previousRank": 52,
      "rankChange": 0,
      "isNew": false,
      "appleId": "375526217",
      "name": "Roastmaster",
      "developer": "Rainfrog, Inc.",
      "developerUrl": "https://apps.apple.com/jp/developer/rainfrog-inc/id375526220?uo=2",
      "iconUrl": "https://is1-ssl.mzstatic.com/image/thumb/Purple124/v4/fb/f0/d6/fbf0d612-7216-abb1-79f0-fe1517fa4368/AppIcon-0-0-1x_U007emarketing-0-0-0-7-0-0-sRGB-0-0-0-GLES2_U002c0-512MB-85-220-0-0.png/100x100bb.png",
      "storeUrl": "https://apps.apple.com/jp/app/roastmaster/id375526217?uo=2",
      "price": {
        "amount": 1500,
        "currency": "JPY",
        "formatted": "¥1,500"
      },
      "primaryCategory": {
        "id": "6023",
        "name": "フード／ドリンク"
      },
      "releaseDate": "2010年6月4日"
    },
    {
      "rank": 53,
      "previousRank": 53,
      "rankChange": 0,
      "isNew": false,
      "appleId": "672175251",
      "name": "Caveman Feast - Paleo Recipes",
      "developer": "Nibble Apps Ltd",
      "developerUrl": "https://apps.apple.com/jp/developer/nibble-apps-ltd/id900888256?uo=2",
      "iconUrl": "https://is1-ssl.mzstatic.com/image/thumb/Purple118/v4/f5/0c/26/f50c2603-065f-cc19-675e-7e6d92ead70e/AppIcon-0-1x_U007emarketing-0-0-GLES2_U002c0-512MB-sRGB-0-0-0-85-220-0-0-0-7.png/100x100bb.png",
      "storeUrl": "https://apps.apple.com/jp/app/caveman-feast-paleo-recipes/id672175251?uo=2",
      "price": {
        "amount": 500,
        "currency": "JPY",
        "formatted": "¥500"
      },
      "primaryCategory": {
        "id": "6023",
        "name": "フード／ドリンク"
      },
      "releaseDate": "2013年7月22日"
    },
    {
      "rank": 54,
      "previousRank": 54,
      "rankChange": 0,
      "isNew": false,
      "appleId": "1342514392",
      "name": "Filipino Food Recipes & Dishes",
      "developer": "Gorasiya Vishal Nanjibhai",
      "developerUrl": "https://apps.apple.com/jp/developer/gorasiya-vishal-nanjibhai/id1287086933?uo=2",
      "iconUrl": "https://is1-ssl.mzstatic.com/image/thumb/Purple211/v4/6e/09/da/6e09dad1-349d-c60d-48c2-b1c9b6b87542/AppIcon-1x_U007emarketing-0-10-0-85-220-0.png/100x100bb.png",
      "storeUrl": "https://apps.apple.com/jp/app/filipino-food-recipes-dishes/id1342514392?uo=2",
      "price": {
        "amount": 600,
        "currency": "JPY",
        "formatted": "¥600"
      },
      "primaryCategory": {
        "id": "6023",
        "name": "フード／ドリンク"
      },
      "releaseDate": "2018年4月5日"
    },
    {
      "rank": 55,
      "previousRank": 55,
      "rankChange": 0,
      "isNew": false,
      "appleId": "1032173485",
      "name": "中食カロリー糖質摂取計算アプリ",
      "developer": "Takaaki Sasaki",
      "developerUrl": "https://apps.apple.com/jp/developer/takaaki-sasaki/id525616408?uo=2",
      "iconUrl": "https://is1-ssl.mzstatic.com/image/thumb/Purple126/v4/c3/40/e8/c340e84d-3b98-5ae1-c305-68d161ac5431/AppIcon-1x_U007emarketing-0-5-85-220.png/100x100bb.png",
      "storeUrl": "https://apps.apple.com/jp/app/%E4%B8%AD%E9%A3%9F%E3%82%AB%E3%83%AD%E3%83%AA%E3%83%BC%E7%B3%96%E8%B3%AA%E6%91%82%E5%8F%96%E8%A8%88%E7%AE%97%E3%82%A2%E3%83%97%E3%83%AA/id1032173485?uo=2",
      "price": {
        "amount": 150,
        "currency": "JPY",
        "formatted": "¥150"
      },
      "primaryCategory": {
        "id": "6023",
        "name": "フード／ドリンク"
      },
      "releaseDate": "2015年8月27日"
    },
    {
      "rank": 56,
      "previousRank": 56,
      "rankChange": 0,
      "isNew": false,
      "appleId": "928904094",
      "name": "Cocktail Party: Drink Recipes",
      "developer": "Cooper Bold Interactive",
      "developerUrl": "https://apps.apple.com/jp/developer/cooper-bold-interactive/id928904093?uo=2",
      "iconUrl": "https://is1-ssl.mzstatic.com/image/thumb/Purple221/v4/47/7e/ff/477eff9a-9a42-aeab-2ac7-63bb14846d60/AppIcon-0-0-1x_U007epad-0-1-85-220.png/100x100bb.png",
      "storeUrl": "https://apps.apple.com/jp/app/cocktail-party-drink-recipes/id928904094?uo=2",
      "price": {
        "amount": 600,
        "currency": "JPY",
        "formatted": "¥600"
      },
      "primaryCategory": {
        "id": "6023",
        "name": "フード／ドリンク"
      },
      "releaseDate": "2014年12月9日"
    },
    {
      "rank": 57,
      "previousRank": 57,
      "rankChange": 0,
      "isNew": false,
      "appleId": "405852650",
      "name": "Lebanese Recipes",
      "developer": "LebGuide.com",
      "developerUrl": "https://apps.apple.com/jp/developer/lebguide-com/id405852653?uo=2",
      "iconUrl": "https://is1-ssl.mzstatic.com/image/thumb/Purple221/v4/36/0f/32/360f3279-c565-b2f8-55c1-3b2ce34fb674/AppIcon-1-0-0-1x_U007ephone-0-1-0-0-P3-85-220.png/100x100bb.png",
      "storeUrl": "https://apps.apple.com/jp/app/lebanese-recipes/id405852650?uo=2",
      "price": {
        "amount": 300,
        "currency": "JPY",
        "formatted": "¥300"
      },
      "primaryCategory": {
        "id": "6023",
        "name": "フード／ドリンク"
      },
      "releaseDate": "2010年12月2日"
    },
    {
      "rank": 58,
      "previousRank": 58,
      "rankChange": 0,
      "isNew": false,
      "appleId": "427132867",
      "name": "소박한 한 그릇",
      "developer": "DaolSoft, Co., Ltd.",
      "developerUrl": "https://apps.apple.com/jp/developer/daolsoft-co-ltd/id295463355?uo=2",
      "iconUrl": "https://is1-ssl.mzstatic.com/image/thumb/Purple211/v4/9c/d8/21/9cd8211d-b65d-e3e0-a277-12127633d69e/AppIcon-0-0-1x_U007emarketing-0-11-0-85-220.png/100x100bb.png",
      "storeUrl": "https://apps.apple.com/jp/app/%EC%86%8C%EB%B0%95%ED%95%9C-%ED%95%9C-%EA%B7%B8%EB%A6%87/id427132867?uo=2",
      "price": {
        "amount": 150,
        "currency": "JPY",
        "formatted": "¥150"
      },
      "primaryCategory": {
        "id": "6023",
        "name": "フード／ドリンク"
      },
      "releaseDate": "2011年3月22日"
    },
    {
      "rank": 59,
      "previousRank": 60,
      "rankChange": 1,
      "isNew": false,
      "appleId": "6742094566",
      "name": "慢吞吞 - 细嚼慢咽养成App",
      "developer": "恺诚 吉",
      "developerUrl": "https://apps.apple.com/jp/developer/%E6%81%BA%E8%AF%9A-%E5%90%89/id1676198101?uo=2",
      "iconUrl": "https://is1-ssl.mzstatic.com/image/thumb/Purple211/v4/b2/49/c4/b249c4d7-75a7-13ab-43ae-ad327694c4c5/AppIcon-0-0-1x_U007epad-0-1-85-220.jpeg/100x100bb.png",
      "storeUrl": "https://apps.apple.com/jp/app/%E6%85%A2%E5%90%9E%E5%90%9E-%E7%BB%86%E5%9A%BC%E6%85%A2%E5%92%BD%E5%85%BB%E6%88%90app/id6742094566?uo=2",
      "price": {
        "amount": 600,
        "currency": "JPY",
        "formatted": "¥600"
      },
      "primaryCategory": {
        "id": "6023",
        "name": "フード／ドリンク"
      },
      "releaseDate": "2025年2月18日"
    },
    {
      "rank": 60,
      "previousRank": 61,
      "rankChange": 1,
      "isNew": false,
      "appleId": "534950419",
      "name": "Tip Calculator % Pro",
      "developer": "Skol Games LLC",
      "developerUrl": "https://apps.apple.com/jp/developer/skol-games-llc/id528519743?uo=2",
      "iconUrl": "https://is1-ssl.mzstatic.com/image/thumb/Purple126/v4/18/d5/0d/18d50d51-0c1a-5bb8-3bfa-3499fd613def/AppIcon-TipcalcPro-1x_U007emarketing-0-3-0-0-85-220.png/100x100bb.png",
      "storeUrl": "https://apps.apple.com/jp/app/tip-calculator-pro/id534950419?uo=2",
      "price": {
        "amount": 2000,
        "currency": "JPY",
        "formatted": "¥2,000"
      },
      "primaryCategory": {
        "id": "6023",
        "name": "フード／ドリンク"
      },
      "releaseDate": "2012年6月19日"
    },
    {
      "rank": 61,
      "previousRank": 62,
      "rankChange": 1,
      "isNew": false,
      "appleId": "419217101",
      "name": "Sous Vide °Celsius",
      "developer": "Jonas Frei",
      "developerUrl": "https://apps.apple.com/jp/developer/jonas-frei/id418712578?uo=2",
      "iconUrl": "https://is1-ssl.mzstatic.com/image/thumb/Purple124/v4/f3/42/fc/f342fc54-5f85-6e04-ab26-2c99a2181cf0/AppIcon-0-0-1x_U007emarketing-0-0-0-6-0-0-sRGB-0-0-0-GLES2_U002c0-512MB-85-220-0-0.png/100x100bb.png",
      "storeUrl": "https://apps.apple.com/jp/app/sous-vide-celsius/id419217101?uo=2",
      "price": {
        "amount": 800,
        "currency": "JPY",
        "formatted": "¥800"
      },
      "primaryCategory": {
        "id": "6023",
        "name": "フード／ドリンク"
      },
      "releaseDate": "2011年2月15日"
    },
    {
      "rank": 62,
      "previousRank": 64,
      "rankChange": 2,
      "isNew": false,
      "appleId": "6504242520",
      "name": "コーヒーlog",
      "developer": "Shota Nakayama",
      "developerUrl": "https://apps.apple.com/jp/developer/shota-nakayama/id1738893528?uo=2",
      "iconUrl": "https://is1-ssl.mzstatic.com/image/thumb/Purple211/v4/0c/91/95/0c91959a-9c7c-074d-c431-22559a96300c/AppIcon-0-0-1x_U007emarketing-0-8-0-0-85-220.png/100x100bb.png",
      "storeUrl": "https://apps.apple.com/jp/app/%E3%82%B3%E3%83%BC%E3%83%92%E3%83%BClog/id6504242520?uo=2",
      "price": {
        "amount": 50,
        "currency": "JPY",
        "formatted": "¥50"
      },
      "primaryCategory": {
        "id": "6023",
        "name": "フード／ドリンク"
      },
      "releaseDate": "2024年6月26日"
    },
    {
      "rank": 63,
      "previousRank": 65,
      "rankChange": 2,
      "isNew": false,
      "appleId": "1445352767",
      "name": "SiP coffee finder",
      "developer": "Kuo Hua Lai",
      "developerUrl": "https://apps.apple.com/jp/developer/kuo-hua-lai/id1445352766?uo=2",
      "iconUrl": "https://is1-ssl.mzstatic.com/image/thumb/Purple122/v4/98/98/74/98987444-5bbb-837d-8a40-69eaf8afeba0/AppIcon-1x_U007emarketing-0-6-0-85-220.png/100x100bb.png",
      "storeUrl": "https://apps.apple.com/jp/app/sip-coffee-finder/id1445352767?uo=2",
      "price": {
        "amount": 600,
        "currency": "JPY",
        "formatted": "¥600"
      },
      "primaryCategory": {
        "id": "6023",
        "name": "フード／ドリンク"
      },
      "releaseDate": "2019年5月31日"
    },
    {
      "rank": 64,
      "previousRank": 66,
      "rankChange": 2,
      "isNew": false,
      "appleId": "1340469417",
      "name": "My Fussy Eater",
      "developer": "Ciara Mullan",
      "developerUrl": "https://apps.apple.com/jp/developer/ciara-mullan/id1340469416?uo=2",
      "iconUrl": "https://is1-ssl.mzstatic.com/image/thumb/Purple211/v4/6a/15/24/6a152457-1c39-83a4-c65c-28d06288a70c/AppIcon-0-0-1x_U007emarketing-0-6-0-sRGB-85-220.png/100x100bb.png",
      "storeUrl": "https://apps.apple.com/jp/app/my-fussy-eater/id1340469417?uo=2",
      "price": {
        "amount": 800,
        "currency": "JPY",
        "formatted": "¥800"
      },
      "primaryCategory": {
        "id": "6023",
        "name": "フード／ドリンク"
      },
      "releaseDate": "2018年1月30日"
    },
    {
      "rank": 65,
      "previousRank": 67,
      "rankChange": 2,
      "isNew": false,
      "appleId": "835148977",
      "name": "Beachbum Berry’s Total Tiki",
      "developer": "Doudoroff LLC",
      "developerUrl": "https://apps.apple.com/jp/developer/doudoroff-llc/id404082951?uo=2",
      "iconUrl": "https://is1-ssl.mzstatic.com/image/thumb/Purple122/v4/88/71/3a/88713aa5-21f2-c61e-4842-edd65e1c99aa/AppIcon-tiki3-0-0-1x_U007emarketing-0-0-0-7-0-0-sRGB-0-0-0-GLES2_U002c0-512MB-85-220-0-0.png/100x100bb.png",
      "storeUrl": "https://apps.apple.com/jp/app/beachbum-berrys-total-tiki/id835148977?uo=2",
      "price": {
        "amount": 4000,
        "currency": "JPY",
        "formatted": "¥4,000"
      },
      "primaryCategory": {
        "id": "6023",
        "name": "フード／ドリンク"
      },
      "releaseDate": "2014年4月15日"
    },
    {
      "rank": 66,
      "previousRank": 59,
      "rankChange": -7,
      "isNew": false,
      "appleId": "6790705219",
      "name": "おかわりレシピ",
      "developer": "Susumu Yamanaka",
      "developerUrl": "https://apps.apple.com/jp/developer/susumu-yamanaka/id6790620605?uo=2",
      "iconUrl": "https://is1-ssl.mzstatic.com/image/thumb/Purple221/v4/2b/ad/5a/2bad5ae6-546c-c0b2-0217-c27286ba0733/AppIcon-0-0-1x_U007ephone-0-1-85-220.png/100x100bb.png",
      "storeUrl": "https://apps.apple.com/jp/app/%E3%81%8A%E3%81%8B%E3%82%8F%E3%82%8A%E3%83%AC%E3%82%B7%E3%83%94/id6790705219?uo=2",
      "price": {
        "amount": 100,
        "currency": "JPY",
        "formatted": "¥100"
      },
      "primaryCategory": {
        "id": "6023",
        "name": "フード／ドリンク"
      },
      "releaseDate": "2026年7月15日"
    },
    {
      "rank": 67,
      "previousRank": 63,
      "rankChange": -4,
      "isNew": false,
      "appleId": "6670228620",
      "name": "傾斜割り勘計算機",
      "developer": "Shun Isayama",
      "developerUrl": "https://apps.apple.com/jp/developer/shun-isayama/id1578976556?uo=2",
      "iconUrl": "https://is1-ssl.mzstatic.com/image/thumb/Purple211/v4/fe/d4/9f/fed49f15-24a7-36b0-5860-b9af7b5b3b56/AppIcon-0-0-1x_U007epad-0-1-85-220.png/100x100bb.png",
      "storeUrl": "https://apps.apple.com/jp/app/%E5%82%BE%E6%96%9C%E5%89%B2%E3%82%8A%E5%8B%98%E8%A8%88%E7%AE%97%E6%A9%9F/id6670228620?uo=2",
      "price": {
        "amount": 500,
        "currency": "JPY",
        "formatted": "¥500"
      },
      "primaryCategory": {
        "id": "6023",
        "name": "フード／ドリンク"
      },
      "releaseDate": "2024年8月30日"
    },
    {
      "rank": 68,
      "previousRank": 68,
      "rankChange": 0,
      "isNew": false,
      "appleId": "1061395015",
      "name": "シェフタイマー - 料理の調理",
      "developer": "LionsApp di Nallbati Elton",
      "developerUrl": "https://apps.apple.com/jp/developer/lionsapp-di-nallbati-elton/id432915499?uo=2",
      "iconUrl": "https://is1-ssl.mzstatic.com/image/thumb/Purple211/v4/6d/3b/74/6d3b74a9-b445-8983-e0de-f5e10ab288c3/AppIcon-0-0-1x_U007epad-0-1-0-85-220.png/100x100bb.png",
      "storeUrl": "https://apps.apple.com/jp/app/%E3%82%B7%E3%82%A7%E3%83%95%E3%82%BF%E3%82%A4%E3%83%9E%E3%83%BC-%E6%96%99%E7%90%86%E3%81%AE%E8%AA%BF%E7%90%86/id1061395015?uo=2",
      "price": {
        "amount": 300,
        "currency": "JPY",
        "formatted": "¥300"
      },
      "primaryCategory": {
        "id": "6023",
        "name": "フード／ドリンク"
      },
      "releaseDate": "2015年12月19日"
    },
    {
      "rank": 69,
      "previousRank": 69,
      "rankChange": 0,
      "isNew": false,
      "appleId": "1048878026",
      "name": "Japan Food Addict",
      "developer": "Andy Scearce",
      "developerUrl": "https://apps.apple.com/jp/developer/andy-scearce/id1048878025?uo=2",
      "iconUrl": "https://is1-ssl.mzstatic.com/image/thumb/Purple221/v4/bc/e2/d4/bce2d4ec-878b-60a0-d82a-b389fab61b8d/AppIcon-0-0-1x_U007ephone-0-1-0-85-220.png/100x100bb.png",
      "storeUrl": "https://apps.apple.com/jp/app/japan-food-addict/id1048878026?uo=2",
      "price": {
        "amount": 800,
        "currency": "JPY",
        "formatted": "¥800"
      },
      "primaryCategory": {
        "id": "6023",
        "name": "フード／ドリンク"
      },
      "releaseDate": "2017年7月11日"
    },
    {
      "rank": 70,
      "previousRank": 70,
      "rankChange": 0,
      "isNew": false,
      "appleId": "345119718",
      "name": "Ratio",
      "developer": "Ruhlman Enterprises, Inc.",
      "developerUrl": "https://apps.apple.com/jp/developer/ruhlman-enterprises-inc/id345119721?uo=2",
      "iconUrl": "https://is1-ssl.mzstatic.com/image/thumb/Purple111/v4/bb/8a/70/bb8a70e9-71db-e141-8b22-ed5c1c7c3b85/mzl.ebyyvhqj.png/100x100bb.png",
      "storeUrl": "https://apps.apple.com/jp/app/ratio/id345119718?uo=2",
      "price": {
        "amount": 800,
        "currency": "JPY",
        "formatted": "¥800"
      },
      "primaryCategory": {
        "id": "6023",
        "name": "フード／ドリンク"
      },
      "releaseDate": "2009年12月15日"
    },
    {
      "rank": 71,
      "previousRank": 71,
      "rankChange": 0,
      "isNew": false,
      "appleId": "1447158881",
      "name": "Maja Vase",
      "developer": "Jakob Ambeck Vase",
      "developerUrl": "https://apps.apple.com/jp/developer/jakob-ambeck-vase/id1447158640?uo=2",
      "iconUrl": "https://is1-ssl.mzstatic.com/image/thumb/Purple221/v4/05/8d/ce/058dcef6-da1f-e90c-09a9-8747cc561873/AppIcon-0-0-1x_U007ephone-0-1-85-220.png/100x100bb.png",
      "storeUrl": "https://apps.apple.com/jp/app/maja-vase/id1447158881?uo=2",
      "price": {
        "amount": 1000,
        "currency": "JPY",
        "formatted": "¥1,000"
      },
      "primaryCategory": {
        "id": "6023",
        "name": "フード／ドリンク"
      },
      "releaseDate": "2019年4月14日"
    },
    {
      "rank": 72,
      "previousRank": 72,
      "rankChange": 0,
      "isNew": false,
      "appleId": "896769380",
      "name": "Martin’s Index of Cocktails",
      "developer": "Doudoroff LLC",
      "developerUrl": "https://apps.apple.com/jp/developer/doudoroff-llc/id404082951?uo=2",
      "iconUrl": "https://is1-ssl.mzstatic.com/image/thumb/Purple122/v4/0b/f8/4b/0bf84bef-375a-ce20-f71d-3705fd65bf81/AppIcon-hairball-0-0-1x_U007emarketing-0-0-0-7-0-0-sRGB-0-0-0-GLES2_U002c0-512MB-85-220-0-0.png/100x100bb.png",
      "storeUrl": "https://apps.apple.com/jp/app/martins-index-of-cocktails/id896769380?uo=2",
      "price": {
        "amount": 2000,
        "currency": "JPY",
        "formatted": "¥2,000"
      },
      "primaryCategory": {
        "id": "6023",
        "name": "フード／ドリンク"
      },
      "releaseDate": "2014年7月23日"
    },
    {
      "rank": 73,
      "previousRank": 73,
      "rankChange": 0,
      "isNew": false,
      "appleId": "864979091",
      "name": "Jason Vale’s Super Juice Me!",
      "developer": "Juice Master",
      "developerUrl": "https://apps.apple.com/jp/developer/juice-master/id493242642?uo=2",
      "iconUrl": "https://is1-ssl.mzstatic.com/image/thumb/Purple122/v4/99/d1/2d/99d12d89-9eb5-0cf2-dd94-3e68017d7a0c/AppIcon-0-0-1x_U007emarketing-0-0-0-7-0-0-sRGB-0-0-0-GLES2_U002c0-512MB-85-220-0-0.png/100x100bb.png",
      "storeUrl": "https://apps.apple.com/jp/app/jason-vales-super-juice-me/id864979091?uo=2",
      "price": {
        "amount": 1500,
        "currency": "JPY",
        "formatted": "¥1,500"
      },
      "primaryCategory": {
        "id": "6023",
        "name": "フード／ドリンク"
      },
      "releaseDate": "2014年4月26日"
    },
    {
      "rank": 74,
      "previousRank": 74,
      "rankChange": 0,
      "isNew": false,
      "appleId": "340206461",
      "name": "Find Craft Beer",
      "developer": "Micro Integration Services, Inc.",
      "developerUrl": "https://apps.apple.com/jp/developer/micro-integration-services-inc/id340206464?uo=2",
      "iconUrl": "https://is1-ssl.mzstatic.com/image/thumb/Purple211/v4/56/74/bc/5674bcc1-8a85-1831-17ba-9a6fa59533cd/AppIcon-0-0-1x_U007emarketing-0-8-0-85-220.png/100x100bb.png",
      "storeUrl": "https://apps.apple.com/jp/app/find-craft-beer/id340206461?uo=2",
      "price": {
        "amount": 150,
        "currency": "JPY",
        "formatted": "¥150"
      },
      "primaryCategory": {
        "id": "6023",
        "name": "フード／ドリンク"
      },
      "releaseDate": "2009年12月31日"
    },
    {
      "rank": 75,
      "previousRank": 75,
      "rankChange": 0,
      "isNew": false,
      "appleId": "299488805",
      "name": "Wine Cellar",
      "developer": "Simon Guertin",
      "developerUrl": "https://apps.apple.com/jp/developer/simon-guertin/id299488808?uo=2",
      "iconUrl": "https://is1-ssl.mzstatic.com/image/thumb/Purple211/v4/17/b2/14/17b21419-d615-5a3d-6949-637cfdc557c4/AppIcon-0-0-1x_U007emarketing-0-4-0-85-220.png/100x100bb.png",
      "storeUrl": "https://apps.apple.com/jp/app/wine-cellar/id299488805?uo=2",
      "price": {
        "amount": 150,
        "currency": "JPY",
        "formatted": "¥150"
      },
      "primaryCategory": {
        "id": "6023",
        "name": "フード／ドリンク"
      },
      "releaseDate": "2009年1月8日"
    },
    {
      "rank": 76,
      "previousRank": 76,
      "rankChange": 0,
      "isNew": false,
      "appleId": "1144412117",
      "name": "Krautkopf",
      "developer": "Nibble Apps Ltd",
      "developerUrl": "https://apps.apple.com/jp/developer/nibble-apps-ltd/id900888256?uo=2",
      "iconUrl": "https://is1-ssl.mzstatic.com/image/thumb/Purple118/v4/95/10/29/951029d4-084c-22e3-a848-c8d0270b93ff/AppIcon-0-1x_U007emarketing-0-0-GLES2_U002c0-512MB-sRGB-0-0-0-85-220-0-0-0-6.png/100x100bb.png",
      "storeUrl": "https://apps.apple.com/jp/app/krautkopf/id1144412117?uo=2",
      "price": {
        "amount": 600,
        "currency": "JPY",
        "formatted": "¥600"
      },
      "primaryCategory": {
        "id": "6023",
        "name": "フード／ドリンク"
      },
      "releaseDate": "2016年8月24日"
    },
    {
      "rank": 77,
      "previousRank": 77,
      "rankChange": 0,
      "isNew": false,
      "appleId": "987998708",
      "name": "Поваренок - рецепты c фото",
      "developer": "Ruslan Balkarov",
      "developerUrl": "https://apps.apple.com/jp/developer/ruslan-balkarov/id874348109?uo=2",
      "iconUrl": "https://is1-ssl.mzstatic.com/image/thumb/Purple114/v4/23/ae/cb/23aecbbf-b378-6586-d9d6-8f7e03ef1b1e/AppIcon-0-0-1x_U007emarketing-0-0-0-7-0-0-sRGB-0-0-0-GLES2_U002c0-512MB-85-220-0-0.png/100x100bb.png",
      "storeUrl": "https://apps.apple.com/jp/app/%D0%BF%D0%BE%D0%B2%D0%B0%D1%80%D0%B5%D0%BD%D0%BE%D0%BA-%D1%80%D0%B5%D1%86%D0%B5%D0%BF%D1%82%D1%8B-c-%D1%84%D0%BE%D1%82%D0%BE/id987998708?uo=2",
      "price": {
        "amount": 150,
        "currency": "JPY",
        "formatted": "¥150"
      },
      "primaryCategory": {
        "id": "6023",
        "name": "フード／ドリンク"
      },
      "releaseDate": "2015年4月23日"
    },
    {
      "rank": 78,
      "previousRank": 79,
      "rankChange": 1,
      "isNew": false,
      "appleId": "698174484",
      "name": "Kitchen Scales",
      "developer": "Valgy",
      "developerUrl": "https://apps.apple.com/jp/developer/valgy/id464576000?uo=2",
      "iconUrl": "https://is1-ssl.mzstatic.com/image/thumb/Purple211/v4/6e/bf/4e/6ebf4e83-2994-4f98-8de7-e5e08769affb/AppIcon-0-0-1x_U007emarketing-0-8-0-85-220.png/100x100bb.png",
      "storeUrl": "https://apps.apple.com/jp/app/kitchen-scales/id698174484?uo=2",
      "price": {
        "amount": 300,
        "currency": "JPY",
        "formatted": "¥300"
      },
      "primaryCategory": {
        "id": "6023",
        "name": "フード／ドリンク"
      },
      "releaseDate": "2013年9月12日"
    },
    {
      "rank": 79,
      "previousRank": 80,
      "rankChange": 1,
      "isNew": false,
      "appleId": "372387251",
      "name": "Substitutions",
      "developer": "Gormaya",
      "developerUrl": "https://apps.apple.com/jp/developer/gormaya/id336813706?uo=2",
      "iconUrl": "https://is1-ssl.mzstatic.com/image/thumb/Purple113/v4/06/a8/97/06a89768-a82a-1cd9-e992-92e77823a70d/AppIcon-0-0-1x_U007emarketing-0-0-0-6-0-0-sRGB-0-0-0-GLES2_U002c0-512MB-85-220-0-0.png/100x100bb.png",
      "storeUrl": "https://apps.apple.com/jp/app/substitutions/id372387251?uo=2",
      "price": {
        "amount": 300,
        "currency": "JPY",
        "formatted": "¥300"
      },
      "primaryCategory": {
        "id": "6023",
        "name": "フード／ドリンク"
      },
      "releaseDate": "2010年5月20日"
    },
    {
      "rank": 80,
      "previousRank": 81,
      "rankChange": 1,
      "isNew": false,
      "appleId": "584269128",
      "name": "Yogicfoods -  Global recipes",
      "developer": "Gary Saggu",
      "developerUrl": "https://apps.apple.com/jp/developer/gary-saggu/id465733546?uo=2",
      "iconUrl": "https://is1-ssl.mzstatic.com/image/thumb/Purple211/v4/6a/03/a8/6a03a800-91f3-7ab7-37de-4839cbd2c0c9/AppIcon-0-0-1x_U007emarketing-0-6-0-85-220.png/100x100bb.png",
      "storeUrl": "https://apps.apple.com/jp/app/yogicfoods-global-recipes/id584269128?uo=2",
      "price": {
        "amount": 300,
        "currency": "JPY",
        "formatted": "¥300"
      },
      "primaryCategory": {
        "id": "6023",
        "name": "フード／ドリンク"
      },
      "releaseDate": "2012年12月12日"
    },
    {
      "rank": 81,
      "previousRank": 82,
      "rankChange": 1,
      "isNew": false,
      "appleId": "431504588",
      "name": "Foraging with the \"Wildman\"",
      "developer": "Steve Brill",
      "developerUrl": "https://apps.apple.com/jp/developer/steve-brill/id1527341581?uo=2",
      "iconUrl": "https://is1-ssl.mzstatic.com/image/thumb/Purple126/v4/94/d5/13/94d51340-d025-c560-c811-8a2292c037f8/AppIcon-1x_U007emarketing-0-7-0-85-220.png/100x100bb.png",
      "storeUrl": "https://apps.apple.com/jp/app/foraging-with-the-wildman/id431504588?uo=2",
      "price": {
        "amount": 1500,
        "currency": "JPY",
        "formatted": "¥1,500"
      },
      "primaryCategory": {
        "id": "6023",
        "name": "フード／ドリンク"
      },
      "releaseDate": "2011年4月15日"
    },
    {
      "rank": 82,
      "previousRank": 78,
      "rankChange": -4,
      "isNew": false,
      "appleId": "6789863110",
      "name": "ウイスキーセラー",
      "developer": "Yuki Kanai",
      "developerUrl": "https://apps.apple.com/jp/developer/yuki-kanai/id6789863112?uo=2",
      "iconUrl": "https://is1-ssl.mzstatic.com/image/thumb/Purple211/v4/a8/dd/e6/a8dde619-3166-4fe6-216b-094668f2d0ae/AppIcon-0-0-1x_U007epad-0-1-85-220.png/100x100bb.png",
      "storeUrl": "https://apps.apple.com/jp/app/%E3%82%A6%E3%82%A4%E3%82%B9%E3%82%AD%E3%83%BC%E3%82%BB%E3%83%A9%E3%83%BC/id6789863110?uo=2",
      "price": {
        "amount": 150,
        "currency": "JPY",
        "formatted": "¥150"
      },
      "primaryCategory": {
        "id": "6023",
        "name": "フード／ドリンク"
      },
      "releaseDate": "2026年7月14日"
    },
    {
      "rank": 83,
      "previousRank": 83,
      "rankChange": 0,
      "isNew": false,
      "appleId": "550571383",
      "name": "Yogicfoods - Baking",
      "developer": "Gary Saggu",
      "developerUrl": "https://apps.apple.com/jp/developer/gary-saggu/id465733546?uo=2",
      "iconUrl": "https://is1-ssl.mzstatic.com/image/thumb/Purple221/v4/fc/39/30/fc3930d6-5698-504b-93ab-e57b5876e61d/AppIcon-0-0-1x_U007emarketing-0-6-0-85-220.png/100x100bb.png",
      "storeUrl": "https://apps.apple.com/jp/app/yogicfoods-baking/id550571383?uo=2",
      "price": {
        "amount": 600,
        "currency": "JPY",
        "formatted": "¥600"
      },
      "primaryCategory": {
        "id": "6023",
        "name": "フード／ドリンク"
      },
      "releaseDate": "2012年8月14日"
    },
    {
      "rank": 84,
      "previousRank": 84,
      "rankChange": 0,
      "isNew": false,
      "appleId": "516159934",
      "name": "Food Lover’s Guide to Paris",
      "developer": "Food Lovers & Co. Inc",
      "developerUrl": "https://apps.apple.com/jp/developer/food-lovers-co-inc/id516159937?uo=2",
      "iconUrl": "https://is1-ssl.mzstatic.com/image/thumb/Purple126/v4/cc/30/8d/cc308d5c-462a-4398-a9ba-324ea71a3769/AppIcon-1x_U007emarketing-0-5-0-0-85-220.png/100x100bb.png",
      "storeUrl": "https://apps.apple.com/jp/app/food-lovers-guide-to-paris/id516159934?uo=2",
      "price": {
        "amount": 800,
        "currency": "JPY",
        "formatted": "¥800"
      },
      "primaryCategory": {
        "id": "6023",
        "name": "フード／ドリンク"
      },
      "releaseDate": "2012年4月17日"
    },
    {
      "rank": 85,
      "previousRank": 85,
      "rankChange": 0,
      "isNew": false,
      "appleId": "6739794099",
      "name": "Coffee Buff",
      "developer": "Taito Iikura",
      "developerUrl": "https://apps.apple.com/jp/developer/taito-iikura/id1506013840?uo=2",
      "iconUrl": "https://is1-ssl.mzstatic.com/image/thumb/Purple211/v4/c6/33/3a/c6333a66-0706-db1e-5f5c-712b1b075fe7/AppIcon-0-0-1x_U007ephone-0-1-85-220.jpeg/100x100bb.png",
      "storeUrl": "https://apps.apple.com/jp/app/coffee-buff/id6739794099?uo=2",
      "price": {
        "amount": 500,
        "currency": "JPY",
        "formatted": "¥500"
      },
      "primaryCategory": {
        "id": "6023",
        "name": "フード／ドリンク"
      },
      "releaseDate": "2024年12月26日"
    },
    {
      "rank": 86,
      "previousRank": 86,
      "rankChange": 0,
      "isNew": false,
      "appleId": "617996793",
      "name": "Jason Vale’s 5-Day Juice Diet",
      "developer": "Juice Master",
      "developerUrl": "https://apps.apple.com/jp/developer/juice-master/id493242642?uo=2",
      "iconUrl": "https://is1-ssl.mzstatic.com/image/thumb/Purple112/v4/12/7f/83/127f8369-fcb5-5c17-b5f5-cf2218fa534f/AppIcon-0-0-1x_U007emarketing-0-0-0-7-0-0-sRGB-0-0-0-GLES2_U002c0-512MB-85-220-0-0.png/100x100bb.png",
      "storeUrl": "https://apps.apple.com/jp/app/jason-vales-5-day-juice-diet/id617996793?uo=2",
      "price": {
        "amount": 800,
        "currency": "JPY",
        "formatted": "¥800"
      },
      "primaryCategory": {
        "id": "6023",
        "name": "フード／ドリンク"
      },
      "releaseDate": "2013年3月19日"
    },
    {
      "rank": 87,
      "previousRank": 87,
      "rankChange": 0,
      "isNew": false,
      "appleId": "568868720",
      "name": "Jason Vale’s 3-Day Juice Diet",
      "developer": "Juice Master",
      "developerUrl": "https://apps.apple.com/jp/developer/juice-master/id493242642?uo=2",
      "iconUrl": "https://is1-ssl.mzstatic.com/image/thumb/Purple122/v4/94/3b/6b/943b6b7e-2987-7e87-b4f7-2431b0a542d9/AppIcon-0-0-1x_U007emarketing-0-0-0-7-0-0-sRGB-0-0-0-GLES2_U002c0-512MB-85-220-0-0.png/100x100bb.png",
      "storeUrl": "https://apps.apple.com/jp/app/jason-vales-3-day-juice-diet/id568868720?uo=2",
      "price": {
        "amount": 500,
        "currency": "JPY",
        "formatted": "¥500"
      },
      "primaryCategory": {
        "id": "6023",
        "name": "フード／ドリンク"
      },
      "releaseDate": "2012年11月1日"
    },
    {
      "rank": 88,
      "previousRank": 88,
      "rankChange": 0,
      "isNew": false,
      "appleId": "506886493",
      "name": "Ask The Butcher",
      "developer": "Vic's Premium Quality Meat",
      "developerUrl": "https://apps.apple.com/jp/developer/vics-premium-quality-meat/id506886496?uo=2",
      "iconUrl": "https://is1-ssl.mzstatic.com/image/thumb/Purple2/v4/78/3c/3d/783c3d74-de79-b43f-fcc5-d350c345ce01/mzl.auhpzbyq.png/100x100bb.png",
      "storeUrl": "https://apps.apple.com/jp/app/ask-the-butcher/id506886493?uo=2",
      "price": {
        "amount": 500,
        "currency": "JPY",
        "formatted": "¥500"
      },
      "primaryCategory": {
        "id": "6023",
        "name": "フード／ドリンク"
      },
      "releaseDate": "2012年3月24日"
    },
    {
      "rank": 89,
      "previousRank": 89,
      "rankChange": 0,
      "isNew": false,
      "appleId": "1324287921",
      "name": "CoffeeDice",
      "developer": "Campion Fellin",
      "developerUrl": "https://apps.apple.com/jp/developer/campion-fellin/id1065809631?uo=2",
      "iconUrl": "https://is1-ssl.mzstatic.com/image/thumb/Purple124/v4/16/69/db/1669dbca-2fe9-d2b4-a0de-d74fffccac62/AppIcon-1x_U007emarketing-0-7-0-85-220.png/100x100bb.png",
      "storeUrl": "https://apps.apple.com/jp/app/coffeedice/id1324287921?uo=2",
      "price": {
        "amount": 150,
        "currency": "JPY",
        "formatted": "¥150"
      },
      "primaryCategory": {
        "id": "6023",
        "name": "フード／ドリンク"
      },
      "releaseDate": "2017年12月12日"
    },
    {
      "rank": 90,
      "previousRank": 90,
      "rankChange": 0,
      "isNew": false,
      "appleId": "1245063271",
      "name": "Daily Blends Recipes",
      "developer": "Simple Green Smoothies, LLC",
      "developerUrl": "https://apps.apple.com/jp/developer/simple-green-smoothies-llc/id1245063270?uo=2",
      "iconUrl": "https://is1-ssl.mzstatic.com/image/thumb/Purple114/v4/d1/ef/e2/d1efe2ba-07bb-84e2-97c9-caa2cfbd6d9f/AppIcon-1x_U007emarketing-0-5-0-85-220.png/100x100bb.png",
      "storeUrl": "https://apps.apple.com/jp/app/daily-blends-recipes/id1245063271?uo=2",
      "price": {
        "amount": 800,
        "currency": "JPY",
        "formatted": "¥800"
      },
      "primaryCategory": {
        "id": "6023",
        "name": "フード／ドリンク"
      },
      "releaseDate": "2017年8月16日"
    },
    {
      "rank": 91,
      "previousRank": 91,
      "rankChange": 0,
      "isNew": false,
      "appleId": "661926224",
      "name": "Italian Food Decoder",
      "developer": "Agorite",
      "developerUrl": "https://apps.apple.com/jp/developer/agorite/id905197684?uo=2",
      "iconUrl": "https://is1-ssl.mzstatic.com/image/thumb/Purple221/v4/ca/c4/dd/cac4dd66-b1a8-b296-1be8-cbe10c7c7083/AppIcon-0-0-1x_U007epad-0-1-85-220.png/100x100bb.png",
      "storeUrl": "https://apps.apple.com/jp/app/italian-food-decoder/id661926224?uo=2",
      "price": {
        "amount": 1000,
        "currency": "JPY",
        "formatted": "¥1,000"
      },
      "primaryCategory": {
        "id": "6023",
        "name": "フード／ドリンク"
      },
      "releaseDate": "2013年6月24日"
    },
    {
      "rank": 92,
      "previousRank": 92,
      "rankChange": 0,
      "isNew": false,
      "appleId": "495582698",
      "name": "Veggie Meals",
      "developer": "Filibaba AB",
      "developerUrl": "https://apps.apple.com/jp/developer/filibaba-ab/id766377303?uo=2",
      "iconUrl": "https://is1-ssl.mzstatic.com/image/thumb/Purple122/v4/f4/62/e1/f462e101-8902-36f4-37ef-5d43a7e3c81e/Meals_Icon-0-0-1x_U007emarketing-0-7-0-0-sRGB-85-220.png/100x100bb.png",
      "storeUrl": "https://apps.apple.com/jp/app/veggie-meals/id495582698?uo=2",
      "price": {
        "amount": 150,
        "currency": "JPY",
        "formatted": "¥150"
      },
      "primaryCategory": {
        "id": "6023",
        "name": "フード／ドリンク"
      },
      "releaseDate": "2012年1月30日"
    },
    {
      "rank": 93,
      "previousRank": 93,
      "rankChange": 0,
      "isNew": false,
      "appleId": "646877156",
      "name": "Recipe Costing Calculator",
      "developer": "Peter Allday",
      "developerUrl": "https://apps.apple.com/jp/developer/peter-allday/id368070262?uo=2",
      "iconUrl": "https://is1-ssl.mzstatic.com/image/thumb/Purple211/v4/0f/77/58/0f7758c9-2c0a-c780-d04a-cca4475b3f11/AppIcon-0-0-1x_U007emarketing-0-7-0-85-220.png/100x100bb.png",
      "storeUrl": "https://apps.apple.com/jp/app/recipe-costing-calculator/id646877156?uo=2",
      "price": {
        "amount": 300,
        "currency": "JPY",
        "formatted": "¥300"
      },
      "primaryCategory": {
        "id": "6023",
        "name": "フード／ドリンク"
      },
      "releaseDate": "2013年5月15日"
    },
    {
      "rank": 94,
      "previousRank": 95,
      "rankChange": 1,
      "isNew": false,
      "appleId": "1131628820",
      "name": "The Tea App",
      "developer": "Baglan Dosmagambetov",
      "developerUrl": "https://apps.apple.com/jp/developer/baglan-dosmagambetov/id429890736?uo=2",
      "iconUrl": "https://is1-ssl.mzstatic.com/image/thumb/Purple118/v4/b7/f5/30/b7f53095-bae8-5d6d-0812-1191251ade29/AppIcon-0-1x_U007emarketing-0-0-GLES2_U002c0-512MB-sRGB-0-0-0-85-220-0-0-0-7.png/100x100bb.png",
      "storeUrl": "https://apps.apple.com/jp/app/the-tea-app/id1131628820?uo=2",
      "price": {
        "amount": 300,
        "currency": "JPY",
        "formatted": "¥300"
      },
      "primaryCategory": {
        "id": "6023",
        "name": "フード／ドリンク"
      },
      "releaseDate": "2016年10月5日"
    },
    {
      "rank": 95,
      "previousRank": 96,
      "rankChange": 1,
      "isNew": false,
      "appleId": "570972794",
      "name": "Rawtarian's Raw Recipes",
      "developer": "Brightflock",
      "developerUrl": "https://apps.apple.com/jp/developer/brightflock/id570972799?uo=2",
      "iconUrl": "https://is1-ssl.mzstatic.com/image/thumb/Purple113/v4/38/f3/c1/38f3c19c-b62a-0cd9-18b5-faacd14a84ac/AppIcon-0-0-1x_U007emarketing-0-0-0-10-0-0-sRGB-0-0-0-GLES2_U002c0-512MB-85-220-0-0.png/100x100bb.png",
      "storeUrl": "https://apps.apple.com/jp/app/rawtarians-raw-recipes/id570972794?uo=2",
      "price": {
        "amount": 500,
        "currency": "JPY",
        "formatted": "¥500"
      },
      "primaryCategory": {
        "id": "6023",
        "name": "フード／ドリンク"
      },
      "releaseDate": "2012年11月2日"
    },
    {
      "rank": 96,
      "previousRank": 97,
      "rankChange": 1,
      "isNew": false,
      "appleId": "368062195",
      "name": "Conversions - Bake & Cook",
      "developer": "Gormaya",
      "developerUrl": "https://apps.apple.com/jp/developer/gormaya/id336813706?uo=2",
      "iconUrl": "https://is1-ssl.mzstatic.com/image/thumb/Purple128/v4/1e/ef/de/1eefde55-8da4-d407-e2c4-8c35775deba9/AppIcon-0-1x_U007emarketing-0-0-85-220-6.png/100x100bb.png",
      "storeUrl": "https://apps.apple.com/jp/app/conversions-bake-cook/id368062195?uo=2",
      "price": {
        "amount": 300,
        "currency": "JPY",
        "formatted": "¥300"
      },
      "primaryCategory": {
        "id": "6023",
        "name": "フード／ドリンク"
      },
      "releaseDate": "2010年4月20日"
    },
    {
      "rank": 97,
      "previousRank": 98,
      "rankChange": 1,
      "isNew": false,
      "appleId": "319592815",
      "name": "Smart Chef - Cooking Helper",
      "developer": "Rantek Inc.",
      "developerUrl": "https://apps.apple.com/jp/developer/rantek-inc/id319592818?uo=2",
      "iconUrl": "https://is1-ssl.mzstatic.com/image/thumb/Purple221/v4/50/4b/d3/504bd37a-8648-f0ff-cd87-c3c522b0fdf0/AppIcon-0-0-1x_U007emarketing-0-5-85-220.jpeg/100x100bb.png",
      "storeUrl": "https://apps.apple.com/jp/app/smart-chef-cooking-helper/id319592815?uo=2",
      "price": {
        "amount": 500,
        "currency": "JPY",
        "formatted": "¥500"
      },
      "primaryCategory": {
        "id": "6023",
        "name": "フード／ドリンク"
      },
      "releaseDate": "2009年6月17日"
    },
    {
      "rank": 98,
      "previousRank": 99,
      "rankChange": 1,
      "isNew": false,
      "appleId": "1665399639",
      "name": "Good Cheese",
      "developer": "Flashover Engineering AB",
      "developerUrl": "https://apps.apple.com/jp/developer/flashover-engineering-ab/id1640994074?uo=2",
      "iconUrl": "https://is1-ssl.mzstatic.com/image/thumb/Purple221/v4/2d/ea/8d/2dea8d26-8ca8-e558-67c8-87ac3ca10e90/AppIcon-0-0-1x_U007ephone-0-1-0-sRGB-85-220.png/100x100bb.png",
      "storeUrl": "https://apps.apple.com/jp/app/good-cheese/id1665399639?uo=2",
      "price": {
        "amount": 150,
        "currency": "JPY",
        "formatted": "¥150"
      },
      "primaryCategory": {
        "id": "6023",
        "name": "フード／ドリンク"
      },
      "releaseDate": "2023年4月6日"
    },
    {
      "rank": 99,
      "previousRank": null,
      "rankChange": null,
      "isNew": true,
      "appleId": "1268701944",
      "name": "CellarView Wine Cellar Tracker",
      "developer": "David Ficken",
      "developerUrl": "https://apps.apple.com/jp/developer/david-ficken/id1268701943?uo=2",
      "iconUrl": "https://is1-ssl.mzstatic.com/image/thumb/Purple221/v4/a0/0a/e9/a00ae995-2484-8003-79a9-4212cca040d4/AppIcon-0-0-1x_U007emarketing-0-6-0-85-220.png/100x100bb.png",
      "storeUrl": "https://apps.apple.com/jp/app/cellarview-wine-cellar-tracker/id1268701944?uo=2",
      "price": {
        "amount": 800,
        "currency": "JPY",
        "formatted": "¥800"
      },
      "primaryCategory": {
        "id": "6023",
        "name": "フード／ドリンク"
      },
      "releaseDate": "2017年9月11日"
    }
  ]
}
